<?xml version='1.0' encoding='UTF-8'?>
<acteur xmlns="http://schemas.assemblee-nationale.fr/referentiel">
  <uid xmlns:xsi="http://www.w3.org/2001/XMLSchema-instance" xsi:type="IdActeur_type">PA267324</uid>
  <etatCivil>
    <ident>
      <civ>M.</civ>
      <prenom>Jean-Jacques</prenom>
      <nom>Gaultier</nom>
      <alpha>Gaultier</alpha>
      <trigramme>JGQ</trigramme>
    </ident>
    <infoNaissance>
      <dateNais>1963-07-13</dateNais>
      <villeNais>Épinal</villeNais>
      <depNais>Vosges</depNais>
      <paysNais>France</paysNais>
    </infoNaissance>
    <dateDeces xmlns:xsi="http://www.w3.org/2001/XMLSchema-instance" xsi:nil="true"/>
  </etatCivil>
  <profession>
    <libelleCourant>Médecin biologiste</libelleCourant>
    <socProcINSEE>
      <catSocPro>Professions libérales et assimilés</catSocPro>
      <famSocPro>Cadres et professions intellectuelles supérieures</famSocPro>
    </socProcINSEE>
  </profession>
  <uri_hatvp>https://www.hatvp.fr/pages_nominatives/gaultier-jean-jacques</uri_hatvp>
  <adresses>
    <adresse xmlns:xsi="http://www.w3.org/2001/XMLSchema-instance" xsi:type="AdressePostale_Type">
      <uid>AD387070</uid>
      <type>0</type>
      <typeLibelle>Adresse officielle</typeLibelle>
      <poids>1</poids>
      <adresseDeRattachement xsi:nil="true"/>
      <intitule>Assemblée nationale,</intitule>
      <numeroRue>126</numeroRue>
      <nomRue>Rue de l'Université,</nomRue>
      <complementAdresse xsi:nil="true"/>
      <codePostal>75355</codePostal>
      <ville>Paris 07 SP</ville>
    </adresse>
    <adresse xmlns:xsi="http://www.w3.org/2001/XMLSchema-instance" xsi:type="AdresseMail_Type">
      <uid>AD391246</uid>
      <type>15</type>
      <typeLibelle>Mèl</typeLibelle>
      <poids xsi:nil="true"/>
      <adresseDeRattachement xsi:nil="true"/>
      <valElec>jjgaultier88@gmail.com</valElec>
    </adresse>
    <adresse xmlns:xsi="http://www.w3.org/2001/XMLSchema-instance" xsi:type="AdresseMail_Type">
      <uid>AD391910</uid>
      <type>15</type>
      <typeLibelle>Mèl</typeLibelle>
      <poids xsi:nil="true"/>
      <adresseDeRattachement xsi:nil="true"/>
      <valElec>jean-jacques.gaultier@assemblee-nationale.fr</valElec>
    </adresse>
    <adresse xmlns:xsi="http://www.w3.org/2001/XMLSchema-instance" xsi:type="AdresseSiteWeb_Type">
      <uid>AD734941</uid>
      <type>24</type>
      <typeLibelle>Twitter</typeLibelle>
      <poids xsi:nil="true"/>
      <adresseDeRattachement xsi:nil="true"/>
      <valElec>@JJ_Gaultier</valElec>
    </adresse>
    <adresse xmlns:xsi="http://www.w3.org/2001/XMLSchema-instance" xsi:type="AdresseSiteWeb_Type">
      <uid>AD734943</uid>
      <type>25</type>
      <typeLibelle>Facebook</typeLibelle>
      <poids xsi:nil="true"/>
      <adresseDeRattachement xsi:nil="true"/>
      <valElec>Jean-Jacques-Gaultier-1088303261286818</valElec>
    </adresse>
    <adresse xmlns:xsi="http://www.w3.org/2001/XMLSchema-instance" xsi:type="AdressePostale_Type">
      <uid>AD734945</uid>
      <type>2</type>
      <typeLibelle>Adresse publiée de circonscription</typeLibelle>
      <poids>22</poids>
      <adresseDeRattachement xsi:nil="true"/>
      <intitule>Permanence parlementaire</intitule>
      <numeroRue>116</numeroRue>
      <nomRue>Rue Charles Garnier</nomRue>
      <complementAdresse xsi:nil="true"/>
      <codePostal>88800</codePostal>
      <ville>Vittel</ville>
    </adresse>
    <adresse xmlns:xsi="http://www.w3.org/2001/XMLSchema-instance" xsi:type="AdresseTelephonique_Type">
      <uid>AD734947</uid>
      <type>11</type>
      <typeLibelle>Téléphone</typeLibelle>
      <poids>22</poids>
      <adresseDeRattachement>AD734945</adresseDeRattachement>
      <valElec>03 29 05 83 84</valElec>
    </adresse>
  </adresses>
  <mandats>
    <mandat xmlns:xsi="http://www.w3.org/2001/XMLSchema-instance" xsi:type="MandatMission_Type">
      <uid>PM772791</uid>
      <acteurRef>PA267324</acteurRef>
      <legislature>15</legislature>
      <typeOrgane>MISINFOPRE</typeOrgane>
      <dateDebut>2020-06-22</dateDebut>
      <datePublication>2020-06-23</datePublication>
      <dateFin>2021-01-27</dateFin>
      <preseance>20</preseance>
      <nominPrincipale>1</nominPrincipale>
      <infosQualite>
        <codeQualite>Membre</codeQualite>
        <libQualite>Membre</libQualite>
        <libQualiteSex>Membre</libQualiteSex>
      </infosQualite>
      <organes>
        <organeRef>PO771231</organeRef>
      </organes>
      <libelle xsi:nil="true"/>
      <missionSuivanteRef xsi:nil="true"/>
      <missionPrecedenteRef xsi:nil="true"/>
    </mandat>
    <mandat xmlns:xsi="http://www.w3.org/2001/XMLSchema-instance" xsi:type="MandatSimple_Type">
      <uid>PM745587</uid>
      <acteurRef>PA267324</acteurRef>
      <legislature xsi:nil="true"/>
      <typeOrgane>PARPOL</typeOrgane>
      <dateDebut>2017-12-01</dateDebut>
      <datePublication xsi:nil="true"/>
      <dateFin xsi:nil="true"/>
      <preseance>5</preseance>
      <nominPrincipale>1</nominPrincipale>
      <infosQualite>
        <codeQualite>Membre</codeQualite>
        <libQualite>Membre</libQualite>
        <libQualiteSex>Membre</libQualiteSex>
      </infosQualite>
      <organes>
        <organeRef>PO710396</organeRef>
      </organes>
    </mandat>
    <mandat xmlns:xsi="http://www.w3.org/2001/XMLSchema-instance" xsi:type="MandatSimple_Type">
      <uid>PM738869</uid>
      <acteurRef>PA267324</acteurRef>
      <legislature>15</legislature>
      <typeOrgane>GEVI</typeOrgane>
      <dateDebut>2017-10-03</dateDebut>
      <datePublication xsi:nil="true"/>
      <dateFin xsi:nil="true"/>
      <preseance>20</preseance>
      <nominPrincipale>0</nominPrincipale>
      <infosQualite>
        <codeQualite>Membre</codeQualite>
        <libQualite>Membre</libQualite>
        <libQualiteSex>Membre</libQualiteSex>
      </infosQualite>
      <organes>
        <organeRef>PO733622</organeRef>
      </organes>
    </mandat>
    <mandat xmlns:xsi="http://www.w3.org/2001/XMLSchema-instance" xsi:type="MandatMission_Type">
      <uid>PM741954</uid>
      <acteurRef>PA267324</acteurRef>
      <legislature>15</legislature>
      <typeOrgane>MISINFO</typeOrgane>
      <dateDebut>2017-09-27</dateDebut>
      <datePublication xsi:nil="true"/>
      <dateFin xsi:nil="true"/>
      <preseance>10</preseance>
      <nominPrincipale>1</nominPrincipale>
      <infosQualite>
        <codeQualite>Membre</codeQualite>
        <libQualite>Membre</libQualite>
        <libQualiteSex>Membre</libQualiteSex>
      </infosQualite>
      <organes>
        <organeRef>PO741916</organeRef>
      </organes>
      <libelle xsi:nil="true"/>
      <missionSuivanteRef xsi:nil="true"/>
      <missionPrecedenteRef xsi:nil="true"/>
    </mandat>
    <mandat xmlns:xsi="http://www.w3.org/2001/XMLSchema-instance" xsi:type="MandatSimple_Type">
      <uid>PM731327</uid>
      <acteurRef>PA267324</acteurRef>
      <legislature>15</legislature>
      <typeOrgane>GP</typeOrgane>
      <dateDebut>2017-06-27</dateDebut>
      <datePublication>2017-06-28</datePublication>
      <dateFin xsi:nil="true"/>
      <preseance>20</preseance>
      <nominPrincipale>1</nominPrincipale>
      <infosQualite>
        <codeQualite>Membre</codeQualite>
        <libQualite>Membre du</libQualite>
        <libQualiteSex>Membre du</libQualiteSex>
      </infosQualite>
      <organes>
        <organeRef>PO730934</organeRef>
      </organes>
    </mandat>
    <mandat xmlns:xsi="http://www.w3.org/2001/XMLSchema-instance" xsi:type="MandatSimple_Type">
      <uid>PM731815</uid>
      <acteurRef>PA267324</acteurRef>
      <legislature>15</legislature>
      <typeOrgane>COMPER</typeOrgane>
      <dateDebut>2017-06-29</dateDebut>
      <datePublication>2017-06-29</datePublication>
      <dateFin xsi:nil="true"/>
      <preseance>32</preseance>
      <nominPrincipale>1</nominPrincipale>
      <infosQualite>
        <codeQualite>Membre</codeQualite>
        <libQualite>Membre</libQualite>
        <libQualiteSex>Membre</libQualiteSex>
      </infosQualite>
      <organes>
        <organeRef>PO419604</organeRef>
      </organes>
    </mandat>
    <mandat xmlns:xsi="http://www.w3.org/2001/XMLSchema-instance" xsi:type="MandatSimple_Type">
      <uid>PM743106</uid>
      <acteurRef>PA267324</acteurRef>
      <legislature>15</legislature>
      <typeOrgane>GEVI</typeOrgane>
      <dateDebut>2017-11-14</dateDebut>
      <datePublication xsi:nil="true"/>
      <dateFin xsi:nil="true"/>
      <preseance>8</preseance>
      <nominPrincipale>1</nominPrincipale>
      <infosQualite>
        <codeQualite>Vice-Président</codeQualite>
        <libQualite>Vice-Président</libQualite>
        <libQualiteSex>Vice-Président</libQualiteSex>
      </infosQualite>
      <organes>
        <organeRef>PO733622</organeRef>
      </organes>
    </mandat>
    <mandat xmlns:xsi="http://www.w3.org/2001/XMLSchema-instance" xsi:type="MandatSimple_Type">
      <uid>PM783946</uid>
      <acteurRef>PA267324</acteurRef>
      <legislature>15</legislature>
      <typeOrgane>CMP</typeOrgane>
      <dateDebut>2021-06-25</dateDebut>
      <datePublication>2021-06-26</datePublication>
      <dateFin>2021-09-29</dateFin>
      <preseance>20</preseance>
      <nominPrincipale>1</nominPrincipale>
      <infosQualite>
        <codeQualite>Titulaire</codeQualite>
        <libQualite>Membre titulaire</libQualite>
        <libQualiteSex>Membre titulaire</libQualiteSex>
      </infosQualite>
      <organes>
        <organeRef>PO783905</organeRef>
      </organes>
    </mandat>
    <mandat xmlns:xsi="http://www.w3.org/2001/XMLSchema-instance" xsi:type="MandatSimple_Type">
      <uid>PM783914</uid>
      <acteurRef>PA267324</acteurRef>
      <legislature>15</legislature>
      <typeOrgane>CMP</typeOrgane>
      <dateDebut>2021-06-25</dateDebut>
      <datePublication>2021-06-26</datePublication>
      <dateFin>2021-09-29</dateFin>
      <preseance>20</preseance>
      <nominPrincipale>1</nominPrincipale>
      <infosQualite>
        <codeQualite>Titulaire</codeQualite>
        <libQualite>Membre titulaire</libQualite>
        <libQualiteSex>Membre titulaire</libQualiteSex>
      </infosQualite>
      <organes>
        <organeRef>PO783898</organeRef>
      </organes>
    </mandat>
    <mandat xmlns:xsi="http://www.w3.org/2001/XMLSchema-instance" xsi:type="MandatSimple_Type">
      <uid>PM755259</uid>
      <acteurRef>PA267324</acteurRef>
      <legislature>15</legislature>
      <typeOrgane>GE</typeOrgane>
      <dateDebut>2018-04-04</dateDebut>
      <datePublication xsi:nil="true"/>
      <dateFin xsi:nil="true"/>
      <preseance>12</preseance>
      <nominPrincipale>1</nominPrincipale>
      <infosQualite>
        <codeQualite>Secrétaire</codeQualite>
        <libQualite>Secrétaire</libQualite>
        <libQualiteSex>Secrétaire</libQualiteSex>
      </infosQualite>
      <organes>
        <organeRef>PO746930</organeRef>
      </organes>
    </mandat>
    <mandat xmlns:xsi="http://www.w3.org/2001/XMLSchema-instance" xsi:type="MandatSimple_Type">
      <uid>PM751263</uid>
      <acteurRef>PA267324</acteurRef>
      <legislature>15</legislature>
      <typeOrgane>GE</typeOrgane>
      <dateDebut>2018-02-19</dateDebut>
      <datePublication xsi:nil="true"/>
      <dateFin xsi:nil="true"/>
      <preseance>20</preseance>
      <nominPrincipale>0</nominPrincipale>
      <infosQualite>
        <codeQualite>Membre</codeQualite>
        <libQualite>Membre</libQualite>
        <libQualiteSex>Membre</libQualiteSex>
      </infosQualite>
      <organes>
        <organeRef>PO747241</organeRef>
      </organes>
    </mandat>
    <mandat xmlns:xsi="http://www.w3.org/2001/XMLSchema-instance" xsi:type="MandatSimple_Type">
      <uid>PM753048</uid>
      <acteurRef>PA267324</acteurRef>
      <legislature>15</legislature>
      <typeOrgane>GE</typeOrgane>
      <dateDebut>2018-03-08</dateDebut>
      <datePublication xsi:nil="true"/>
      <dateFin xsi:nil="true"/>
      <preseance>20</preseance>
      <nominPrincipale>1</nominPrincipale>
      <infosQualite>
        <codeQualite>Membre</codeQualite>
        <libQualite>Membre</libQualite>
        <libQualiteSex>Membre</libQualiteSex>
      </infosQualite>
      <organes>
        <organeRef>PO746811</organeRef>
      </organes>
    </mandat>
    <mandat xmlns:xsi="http://www.w3.org/2001/XMLSchema-instance" xsi:type="MandatSimple_Type">
      <uid>PM751548</uid>
      <acteurRef>PA267324</acteurRef>
      <legislature>15</legislature>
      <typeOrgane>GE</typeOrgane>
      <dateDebut>2018-02-21</dateDebut>
      <datePublication xsi:nil="true"/>
      <dateFin xsi:nil="true"/>
      <preseance>20</preseance>
      <nominPrincipale>1</nominPrincipale>
      <infosQualite>
        <codeQualite>Membre</codeQualite>
        <libQualite>Membre</libQualite>
        <libQualiteSex>Membre</libQualiteSex>
      </infosQualite>
      <organes>
        <organeRef>PO747215</organeRef>
      </organes>
    </mandat>
    <mandat xmlns:xsi="http://www.w3.org/2001/XMLSchema-instance" xsi:type="MandatSimple_Type">
      <uid>PM752393</uid>
      <acteurRef>PA267324</acteurRef>
      <legislature>15</legislature>
      <typeOrgane>GE</typeOrgane>
      <dateDebut>2018-03-05</dateDebut>
      <datePublication xsi:nil="true"/>
      <dateFin xsi:nil="true"/>
      <preseance>20</preseance>
      <nominPrincipale>0</nominPrincipale>
      <infosQualite>
        <codeQualite>Membre</codeQualite>
        <libQualite>Membre</libQualite>
        <libQualiteSex>Membre</libQualiteSex>
      </infosQualite>
      <organes>
        <organeRef>PO746930</organeRef>
      </organes>
    </mandat>
    <mandat xmlns:xsi="http://www.w3.org/2001/XMLSchema-instance" xsi:type="MandatSimple_Type">
      <uid>PM752612</uid>
      <acteurRef>PA267324</acteurRef>
      <legislature>15</legislature>
      <typeOrgane>GE</typeOrgane>
      <dateDebut>2018-03-06</dateDebut>
      <datePublication xsi:nil="true"/>
      <dateFin>2020-01-15</dateFin>
      <preseance>20</preseance>
      <nominPrincipale>1</nominPrincipale>
      <infosQualite>
        <codeQualite>Membre</codeQualite>
        <libQualite>Membre</libQualite>
        <libQualiteSex>Membre</libQualiteSex>
      </infosQualite>
      <organes>
        <organeRef>PO747165</organeRef>
      </organes>
    </mandat>
    <mandat xmlns:xsi="http://www.w3.org/2001/XMLSchema-instance" xsi:type="MandatSimple_Type">
      <uid>PM751532</uid>
      <acteurRef>PA267324</acteurRef>
      <legislature>15</legislature>
      <typeOrgane>GE</typeOrgane>
      <dateDebut>2018-02-21</dateDebut>
      <datePublication xsi:nil="true"/>
      <dateFin xsi:nil="true"/>
      <preseance>20</preseance>
      <nominPrincipale>1</nominPrincipale>
      <infosQualite>
        <codeQualite>Membre</codeQualite>
        <libQualite>Membre</libQualite>
        <libQualiteSex>Membre</libQualiteSex>
      </infosQualite>
      <organes>
        <organeRef>PO746821</organeRef>
      </organes>
    </mandat>
    <mandat xmlns:xsi="http://www.w3.org/2001/XMLSchema-instance" xsi:type="MandatSimple_Type">
      <uid>PM724687</uid>
      <acteurRef>PA267324</acteurRef>
      <legislature>15</legislature>
      <typeOrgane>GP</typeOrgane>
      <dateDebut>2017-06-21</dateDebut>
      <datePublication xsi:nil="true"/>
      <dateFin>2017-06-26</dateFin>
      <preseance>28</preseance>
      <nominPrincipale>1</nominPrincipale>
      <infosQualite>
        <codeQualite>Député non-inscrit</codeQualite>
        <libQualite>Député non-inscrit</libQualite>
        <libQualiteSex>Député non-inscrit</libQualiteSex>
      </infosQualite>
      <organes>
        <organeRef>PO723569</organeRef>
      </organes>
    </mandat>
    <mandat xmlns:xsi="http://www.w3.org/2001/XMLSchema-instance" xsi:type="MandatSimple_Type">
      <uid>PM736944</uid>
      <acteurRef>PA267324</acteurRef>
      <legislature>15</legislature>
      <typeOrgane>GA</typeOrgane>
      <dateDebut>2017-10-03</dateDebut>
      <datePublication xsi:nil="true"/>
      <dateFin xsi:nil="true"/>
      <preseance>20</preseance>
      <nominPrincipale>0</nominPrincipale>
      <infosQualite>
        <codeQualite>Membre</codeQualite>
        <libQualite>Membre</libQualite>
        <libQualiteSex>Membre</libQualiteSex>
      </infosQualite>
      <organes>
        <organeRef>PO733072</organeRef>
      </organes>
    </mandat>
    <mandat xmlns:xsi="http://www.w3.org/2001/XMLSchema-instance" xsi:type="MandatSimple_Type">
      <uid>PM736946</uid>
      <acteurRef>PA267324</acteurRef>
      <legislature>15</legislature>
      <typeOrgane>GA</typeOrgane>
      <dateDebut>2017-10-03</dateDebut>
      <datePublication xsi:nil="true"/>
      <dateFin xsi:nil="true"/>
      <preseance>20</preseance>
      <nominPrincipale>1</nominPrincipale>
      <infosQualite>
        <codeQualite>Membre</codeQualite>
        <libQualite>Membre</libQualite>
        <libQualiteSex>Membre</libQualiteSex>
      </infosQualite>
      <organes>
        <organeRef>PO733117</organeRef>
      </organes>
    </mandat>
    <mandat xmlns:xsi="http://www.w3.org/2001/XMLSchema-instance" xsi:type="MandatSimple_Type">
      <uid>PM747826</uid>
      <acteurRef>PA267324</acteurRef>
      <legislature>15</legislature>
      <typeOrgane>GA</typeOrgane>
      <dateDebut>2018-01-22</dateDebut>
      <datePublication xsi:nil="true"/>
      <dateFin xsi:nil="true"/>
      <preseance>20</preseance>
      <nominPrincipale>1</nominPrincipale>
      <infosQualite>
        <codeQualite>Membre</codeQualite>
        <libQualite>Membre</libQualite>
        <libQualiteSex>Membre</libQualiteSex>
      </infosQualite>
      <organes>
        <organeRef>PO733272</organeRef>
      </organes>
    </mandat>
    <mandat xmlns:xsi="http://www.w3.org/2001/XMLSchema-instance" xsi:type="MandatSimple_Type">
      <uid>PM736948</uid>
      <acteurRef>PA267324</acteurRef>
      <legislature>15</legislature>
      <typeOrgane>GA</typeOrgane>
      <dateDebut>2017-10-03</dateDebut>
      <datePublication xsi:nil="true"/>
      <dateFin xsi:nil="true"/>
      <preseance>20</preseance>
      <nominPrincipale>1</nominPrincipale>
      <infosQualite>
        <codeQualite>Membre</codeQualite>
        <libQualite>Membre</libQualite>
        <libQualiteSex>Membre</libQualiteSex>
      </infosQualite>
      <organes>
        <organeRef>PO733662</organeRef>
      </organes>
    </mandat>
    <mandat xmlns:xsi="http://www.w3.org/2001/XMLSchema-instance" xsi:type="MandatSimple_Type">
      <uid>PM747828</uid>
      <acteurRef>PA267324</acteurRef>
      <legislature>15</legislature>
      <typeOrgane>GA</typeOrgane>
      <dateDebut>2018-01-22</dateDebut>
      <datePublication xsi:nil="true"/>
      <dateFin xsi:nil="true"/>
      <preseance>20</preseance>
      <nominPrincipale>1</nominPrincipale>
      <infosQualite>
        <codeQualite>Membre</codeQualite>
        <libQualite>Membre</libQualite>
        <libQualiteSex>Membre</libQualiteSex>
      </infosQualite>
      <organes>
        <organeRef>PO733562</organeRef>
      </organes>
    </mandat>
    <mandat xmlns:xsi="http://www.w3.org/2001/XMLSchema-instance" xsi:type="MandatSimple_Type">
      <uid>PM746308</uid>
      <acteurRef>PA267324</acteurRef>
      <legislature>15</legislature>
      <typeOrgane>GA</typeOrgane>
      <dateDebut>2017-11-08</dateDebut>
      <datePublication xsi:nil="true"/>
      <dateFin xsi:nil="true"/>
      <preseance>14</preseance>
      <nominPrincipale>1</nominPrincipale>
      <infosQualite>
        <codeQualite>Secrétaire</codeQualite>
        <libQualite>Secrétaire</libQualite>
        <libQualiteSex>Secrétaire</libQualiteSex>
      </infosQualite>
      <organes>
        <organeRef>PO733072</organeRef>
      </organes>
    </mandat>
    <mandat xmlns:xsi="http://www.w3.org/2001/XMLSchema-instance" xsi:type="MandatSimple_Type">
      <uid>PM742353</uid>
      <acteurRef>PA267324</acteurRef>
      <legislature>15</legislature>
      <typeOrgane>GA</typeOrgane>
      <dateDebut>2017-11-02</dateDebut>
      <datePublication xsi:nil="true"/>
      <dateFin xsi:nil="true"/>
      <preseance>20</preseance>
      <nominPrincipale>1</nominPrincipale>
      <infosQualite>
        <codeQualite>Membre</codeQualite>
        <libQualite>Membre</libQualite>
        <libQualiteSex>Membre</libQualiteSex>
      </infosQualite>
      <organes>
        <organeRef>PO733322</organeRef>
      </organes>
    </mandat>
    <mandat xmlns:xsi="http://www.w3.org/2001/XMLSchema-instance" xsi:type="MandatSimple_Type">
      <uid>PM736945</uid>
      <acteurRef>PA267324</acteurRef>
      <legislature>15</legislature>
      <typeOrgane>GA</typeOrgane>
      <dateDebut>2017-10-03</dateDebut>
      <datePublication xsi:nil="true"/>
      <dateFin xsi:nil="true"/>
      <preseance>20</preseance>
      <nominPrincipale>1</nominPrincipale>
      <infosQualite>
        <codeQualite>Membre</codeQualite>
        <libQualite>Membre</libQualite>
        <libQualiteSex>Membre</libQualiteSex>
      </infosQualite>
      <organes>
        <organeRef>PO733107</organeRef>
      </organes>
    </mandat>
    <mandat xmlns:xsi="http://www.w3.org/2001/XMLSchema-instance" xsi:type="MandatSimple_Type">
      <uid>PM736947</uid>
      <acteurRef>PA267324</acteurRef>
      <legislature>15</legislature>
      <typeOrgane>GA</typeOrgane>
      <dateDebut>2017-10-03</dateDebut>
      <datePublication xsi:nil="true"/>
      <dateFin xsi:nil="true"/>
      <preseance>20</preseance>
      <nominPrincipale>0</nominPrincipale>
      <infosQualite>
        <codeQualite>Membre</codeQualite>
        <libQualite>Membre</libQualite>
        <libQualiteSex>Membre</libQualiteSex>
      </infosQualite>
      <organes>
        <organeRef>PO733607</organeRef>
      </organes>
    </mandat>
    <mandat xmlns:xsi="http://www.w3.org/2001/XMLSchema-instance" xsi:type="MandatSimple_Type">
      <uid>PM747827</uid>
      <acteurRef>PA267324</acteurRef>
      <legislature>15</legislature>
      <typeOrgane>GA</typeOrgane>
      <dateDebut>2018-01-22</dateDebut>
      <datePublication xsi:nil="true"/>
      <dateFin xsi:nil="true"/>
      <preseance>20</preseance>
      <nominPrincipale>1</nominPrincipale>
      <infosQualite>
        <codeQualite>Membre</codeQualite>
        <libQualite>Membre</libQualite>
        <libQualiteSex>Membre</libQualiteSex>
      </infosQualite>
      <organes>
        <organeRef>PO733352</organeRef>
      </organes>
    </mandat>
    <mandat xmlns:xsi="http://www.w3.org/2001/XMLSchema-instance" xsi:type="MandatSimple_Type">
      <uid>PM751639</uid>
      <acteurRef>PA267324</acteurRef>
      <legislature>15</legislature>
      <typeOrgane>GE</typeOrgane>
      <dateDebut>2018-02-21</dateDebut>
      <datePublication xsi:nil="true"/>
      <dateFin xsi:nil="true"/>
      <preseance>8</preseance>
      <nominPrincipale>1</nominPrincipale>
      <infosQualite>
        <codeQualite>Vice-Président</codeQualite>
        <libQualite>Vice-Président</libQualite>
        <libQualiteSex>Vice-Président</libQualiteSex>
      </infosQualite>
      <organes>
        <organeRef>PO747241</organeRef>
      </organes>
    </mandat>
    <mandat xmlns:xsi="http://www.w3.org/2001/XMLSchema-instance" xsi:type="MandatSimple_Type">
      <uid>PM747770</uid>
      <acteurRef>PA267324</acteurRef>
      <legislature>15</legislature>
      <typeOrgane>GA</typeOrgane>
      <dateDebut>2017-10-25</dateDebut>
      <datePublication xsi:nil="true"/>
      <dateFin xsi:nil="true"/>
      <preseance>8</preseance>
      <nominPrincipale>1</nominPrincipale>
      <infosQualite>
        <codeQualite>Vice-Président</codeQualite>
        <libQualite>Vice-Président</libQualite>
        <libQualiteSex>Vice-Président</libQualiteSex>
      </infosQualite>
      <organes>
        <organeRef>PO733607</organeRef>
      </organes>
    </mandat>
    <mandat xmlns:xsi="http://www.w3.org/2001/XMLSchema-instance" xsi:type="MandatParlementaire_type">
      <uid>PM723292</uid>
      <acteurRef>PA267324</acteurRef>
      <legislature>15</legislature>
      <typeOrgane>ASSEMBLEE</typeOrgane>
      <dateDebut>2017-06-18</dateDebut>
      <datePublication xsi:nil="true"/>
      <dateFin xsi:nil="true"/>
      <preseance>50</preseance>
      <nominPrincipale>1</nominPrincipale>
      <infosQualite>
        <codeQualite>membre</codeQualite>
        <libQualite>membre</libQualite>
        <libQualiteSex>membre</libQualiteSex>
      </infosQualite>
      <organes>
        <organeRef>PO717460</organeRef>
      </organes>
      <suppleants>
        <suppleant>
          <dateDebut>2017-06-18</dateDebut>
          <dateFin xsi:nil="true"/>
          <suppleantRef>PA721494</suppleantRef>
        </suppleant>
      </suppleants>
      <chambre xsi:nil="true"/>
      <election>
        <lieu>
          <region>Grand Est</region>
          <regionType>Métropolitain</regionType>
          <departement>Vosges</departement>
          <numDepartement>88</numDepartement>
          <numCirco>4</numCirco>
        </lieu>
        <causeMandat>élections générales</causeMandat>
        <refCirconscription>PO718398</refCirconscription>
      </election>
      <mandature>
        <datePriseFonction>2017-06-21</datePriseFonction>
        <causeFin xsi:nil="true"/>
        <premiereElection>1</premiereElection>
        <placeHemicycle>126</placeHemicycle>
        <mandatRemplaceRef xsi:nil="true"/>
      </mandature>
      <collaborateurs>
        <collaborateur>
          <qualite>Mme</qualite>
          <prenom>Évelyne</prenom>
          <nom>Pathouot</nom>
          <dateDebut xsi:nil="true"/>
          <dateFin xsi:nil="true"/>
        </collaborateur>
        <collaborateur>
          <qualite>Mme</qualite>
          <prenom>Stéphanie</prenom>
          <nom>Bocquet-Deramaix</nom>
          <dateDebut xsi:nil="true"/>
          <dateFin xsi:nil="true"/>
        </collaborateur>
        <collaborateur>
          <qualite>M.</qualite>
          <prenom>Alexandre</prenom>
          <nom>Chopinez</nom>
          <dateDebut xsi:nil="true"/>
          <dateFin xsi:nil="true"/>
        </collaborateur>
      </collaborateurs>
    </mandat>
  </mandats>
</acteur>
