<?xml version='1.0' encoding='UTF-8'?>
<acteur xmlns="http://schemas.assemblee-nationale.fr/referentiel">
  <uid xmlns:xsi="http://www.w3.org/2001/XMLSchema-instance" xsi:type="IdActeur_type">PA721262</uid>
  <etatCivil>
    <ident>
      <civ>M.</civ>
      <prenom>Guillaume</prenom>
      <nom>Vuilletet</nom>
      <alpha>Vuilletet</alpha>
      <trigramme>GVU</trigramme>
    </ident>
    <infoNaissance>
      <dateNais>1967-06-20</dateNais>
      <villeNais>Beauvais</villeNais>
      <depNais>Oise</depNais>
      <paysNais>France</paysNais>
    </infoNaissance>
    <dateDeces xmlns:xsi="http://www.w3.org/2001/XMLSchema-instance" xsi:nil="true"/>
  </etatCivil>
  <profession>
    <libelleCourant>Cadre supérieur (secteur privé)</libelleCourant>
    <socProcINSEE>
      <catSocPro>Cadres d'entreprise</catSocPro>
      <famSocPro>Cadres et professions intellectuelles supérieures</famSocPro>
    </socProcINSEE>
  </profession>
  <uri_hatvp>https://www.hatvp.fr/pages_nominatives/vuilletet-guillaume</uri_hatvp>
  <adresses>
    <adresse xmlns:xsi="http://www.w3.org/2001/XMLSchema-instance" xsi:type="AdressePostale_Type">
      <uid>AD721264</uid>
      <type>0</type>
      <typeLibelle>Adresse officielle</typeLibelle>
      <poids>1</poids>
      <adresseDeRattachement xsi:nil="true"/>
      <intitule>Assemblée nationale,</intitule>
      <numeroRue>126</numeroRue>
      <nomRue>Rue de l'Université,</nomRue>
      <complementAdresse xsi:nil="true"/>
      <codePostal>75355</codePostal>
      <ville>Paris 07 SP</ville>
    </adresse>
    <adresse xmlns:xsi="http://www.w3.org/2001/XMLSchema-instance" xsi:type="AdresseSiteWeb_Type">
      <uid>AD726270</uid>
      <type>24</type>
      <typeLibelle>Twitter</typeLibelle>
      <poids xsi:nil="true"/>
      <adresseDeRattachement xsi:nil="true"/>
      <valElec>@g_vuilletet</valElec>
    </adresse>
    <adresse xmlns:xsi="http://www.w3.org/2001/XMLSchema-instance" xsi:type="AdresseSiteWeb_Type">
      <uid>AD726632</uid>
      <type>25</type>
      <typeLibelle>Facebook</typeLibelle>
      <poids xsi:nil="true"/>
      <adresseDeRattachement xsi:nil="true"/>
      <valElec>guillaume.vuilletet</valElec>
    </adresse>
    <adresse xmlns:xsi="http://www.w3.org/2001/XMLSchema-instance" xsi:type="AdresseMail_Type">
      <uid>AD728231</uid>
      <type>15</type>
      <typeLibelle>Mèl</typeLibelle>
      <poids xsi:nil="true"/>
      <adresseDeRattachement xsi:nil="true"/>
      <valElec>guillaume.vuilletet@assemblee-nationale.fr</valElec>
    </adresse>
    <adresse xmlns:xsi="http://www.w3.org/2001/XMLSchema-instance" xsi:type="AdressePostale_Type">
      <uid>AD750238</uid>
      <type>2</type>
      <typeLibelle>Adresse publiée de circonscription</typeLibelle>
      <poids>2</poids>
      <adresseDeRattachement xsi:nil="true"/>
      <intitule>Permanence parlementaire     </intitule>
      <numeroRue>89</numeroRue>
      <nomRue>Marcel Perrin</nomRue>
      <complementAdresse xsi:nil="true"/>
      <codePostal>95540</codePostal>
      <ville>Mery-sur-Oise</ville>
    </adresse>
    <adresse xmlns:xsi="http://www.w3.org/2001/XMLSchema-instance" xsi:type="AdresseMail_Type">
      <uid>AD750240</uid>
      <type>15</type>
      <typeLibelle>Mèl</typeLibelle>
      <poids>2</poids>
      <adresseDeRattachement>AD750238</adresseDeRattachement>
      <valElec>franck.besson@clb-an.fr</valElec>
    </adresse>
    <adresse xmlns:xsi="http://www.w3.org/2001/XMLSchema-instance" xsi:type="AdresseTelephonique_Type">
      <uid>AD750242</uid>
      <type>11</type>
      <typeLibelle>Téléphone</typeLibelle>
      <poids>2</poids>
      <adresseDeRattachement>AD750238</adresseDeRattachement>
      <valElec>01 34 67 74 58</valElec>
    </adresse>
  </adresses>
  <mandats>
    <mandat xmlns:xsi="http://www.w3.org/2001/XMLSchema-instance" xsi:type="MandatSimple_Type">
      <uid>PM732756</uid>
      <acteurRef>PA721262</acteurRef>
      <legislature>15</legislature>
      <typeOrgane>DELEGBUREAU</typeOrgane>
      <dateDebut>2017-06-29</dateDebut>
      <datePublication xsi:nil="true"/>
      <dateFin>2019-10-21</dateFin>
      <preseance>24</preseance>
      <nominPrincipale>1</nominPrincipale>
      <infosQualite>
        <codeQualite>Membre</codeQualite>
        <libQualite>Membre</libQualite>
        <libQualiteSex>Membre</libQualiteSex>
      </infosQualite>
      <organes>
        <organeRef>PO732748</organeRef>
      </organes>
    </mandat>
    <mandat xmlns:xsi="http://www.w3.org/2001/XMLSchema-instance" xsi:type="MandatSimple_Type">
      <uid>PM732786</uid>
      <acteurRef>PA721262</acteurRef>
      <legislature>15</legislature>
      <typeOrgane>DELEGBUREAU</typeOrgane>
      <dateDebut>2017-06-29</dateDebut>
      <datePublication xsi:nil="true"/>
      <dateFin>2019-10-21</dateFin>
      <preseance>24</preseance>
      <nominPrincipale>1</nominPrincipale>
      <infosQualite>
        <codeQualite>Membre</codeQualite>
        <libQualite>Membre</libQualite>
        <libQualiteSex>Membre</libQualiteSex>
      </infosQualite>
      <organes>
        <organeRef>PO732781</organeRef>
      </organes>
    </mandat>
    <mandat xmlns:xsi="http://www.w3.org/2001/XMLSchema-instance" xsi:type="MandatSimple_Type">
      <uid>PM776359</uid>
      <acteurRef>PA721262</acteurRef>
      <legislature>15</legislature>
      <typeOrgane>DELEG</typeOrgane>
      <dateDebut>2020-10-28</dateDebut>
      <datePublication>2020-10-28</datePublication>
      <dateFin xsi:nil="true"/>
      <preseance>20</preseance>
      <nominPrincipale>1</nominPrincipale>
      <infosQualite>
        <codeQualite>Membre</codeQualite>
        <libQualite>Membre</libQualite>
        <libQualiteSex>Membre</libQualiteSex>
      </infosQualite>
      <organes>
        <organeRef>PO675659</organeRef>
      </organes>
    </mandat>
    <mandat xmlns:xsi="http://www.w3.org/2001/XMLSchema-instance" xsi:type="MandatSimple_Type">
      <uid>PM746283</uid>
      <acteurRef>PA721262</acteurRef>
      <legislature>15</legislature>
      <typeOrgane>DELEG</typeOrgane>
      <dateDebut>2017-12-09</dateDebut>
      <datePublication>2017-12-09</datePublication>
      <dateFin>2019-01-30</dateFin>
      <preseance>20</preseance>
      <nominPrincipale>1</nominPrincipale>
      <infosQualite>
        <codeQualite>Membre</codeQualite>
        <libQualite>Membre</libQualite>
        <libQualiteSex>Membre</libQualiteSex>
      </infosQualite>
      <organes>
        <organeRef>PO744127</organeRef>
      </organes>
    </mandat>
    <mandat xmlns:xsi="http://www.w3.org/2001/XMLSchema-instance" xsi:type="MandatMission_Type">
      <uid>PM769874</uid>
      <acteurRef>PA721262</acteurRef>
      <legislature>15</legislature>
      <typeOrgane>MISINFOPRE</typeOrgane>
      <dateDebut>2020-01-29</dateDebut>
      <datePublication>2020-01-30</datePublication>
      <dateFin xsi:nil="true"/>
      <preseance>20</preseance>
      <nominPrincipale>1</nominPrincipale>
      <infosQualite>
        <codeQualite>Membre</codeQualite>
        <libQualite>Membre</libQualite>
        <libQualiteSex>Membre</libQualiteSex>
      </infosQualite>
      <organes>
        <organeRef>PO734384</organeRef>
      </organes>
      <libelle xsi:nil="true"/>
      <missionSuivanteRef xsi:nil="true"/>
      <missionPrecedenteRef xsi:nil="true"/>
    </mandat>
    <mandat xmlns:xsi="http://www.w3.org/2001/XMLSchema-instance" xsi:type="MandatMission_Type">
      <uid>PM784345</uid>
      <acteurRef>PA721262</acteurRef>
      <legislature>15</legislature>
      <typeOrgane>MISINFOPRE</typeOrgane>
      <dateDebut>2021-07-07</dateDebut>
      <datePublication>2021-07-07</datePublication>
      <dateFin>2021-12-08</dateFin>
      <preseance>20</preseance>
      <nominPrincipale>1</nominPrincipale>
      <infosQualite>
        <codeQualite>Membre</codeQualite>
        <libQualite>Membre</libQualite>
        <libQualiteSex>Membre</libQualiteSex>
      </infosQualite>
      <organes>
        <organeRef>PO784318</organeRef>
      </organes>
      <libelle xsi:nil="true"/>
      <missionSuivanteRef xsi:nil="true"/>
      <missionPrecedenteRef xsi:nil="true"/>
    </mandat>
    <mandat xmlns:xsi="http://www.w3.org/2001/XMLSchema-instance" xsi:type="MandatMission_Type">
      <uid>PM742871</uid>
      <acteurRef>PA721262</acteurRef>
      <legislature>15</legislature>
      <typeOrgane>MISINFOCOM</typeOrgane>
      <dateDebut>2017-11-08</dateDebut>
      <datePublication xsi:nil="true"/>
      <dateFin>2018-05-31</dateFin>
      <preseance>20</preseance>
      <nominPrincipale>1</nominPrincipale>
      <infosQualite>
        <codeQualite>Membre</codeQualite>
        <libQualite>Membre</libQualite>
        <libQualiteSex>Membre</libQualiteSex>
      </infosQualite>
      <organes>
        <organeRef>PO742386</organeRef>
      </organes>
      <libelle xsi:nil="true"/>
      <missionSuivanteRef xsi:nil="true"/>
      <missionPrecedenteRef xsi:nil="true"/>
    </mandat>
    <mandat xmlns:xsi="http://www.w3.org/2001/XMLSchema-instance" xsi:type="MandatSimple_Type">
      <uid>PM745517</uid>
      <acteurRef>PA721262</acteurRef>
      <legislature xsi:nil="true"/>
      <typeOrgane>PARPOL</typeOrgane>
      <dateDebut>2017-12-01</dateDebut>
      <datePublication xsi:nil="true"/>
      <dateFin>2018-11-30</dateFin>
      <preseance>5</preseance>
      <nominPrincipale>1</nominPrincipale>
      <infosQualite>
        <codeQualite>Membre</codeQualite>
        <libQualite>Membre</libQualite>
        <libQualiteSex>Membre</libQualiteSex>
      </infosQualite>
      <organes>
        <organeRef>PO744854</organeRef>
      </organes>
    </mandat>
    <mandat xmlns:xsi="http://www.w3.org/2001/XMLSchema-instance" xsi:type="MandatSimple_Type">
      <uid>PM761889</uid>
      <acteurRef>PA721262</acteurRef>
      <legislature xsi:nil="true"/>
      <typeOrgane>PARPOL</typeOrgane>
      <dateDebut>2018-12-01</dateDebut>
      <datePublication xsi:nil="true"/>
      <dateFin xsi:nil="true"/>
      <preseance>5</preseance>
      <nominPrincipale>1</nominPrincipale>
      <infosQualite>
        <codeQualite>Membre</codeQualite>
        <libQualite>Membre</libQualite>
        <libQualiteSex>Membre</libQualiteSex>
      </infosQualite>
      <organes>
        <organeRef>PO761294</organeRef>
      </organes>
    </mandat>
    <mandat xmlns:xsi="http://www.w3.org/2001/XMLSchema-instance" xsi:type="MandatMission_Type">
      <uid>PM750180</uid>
      <acteurRef>PA721262</acteurRef>
      <legislature>15</legislature>
      <typeOrgane>MISINFO</typeOrgane>
      <dateDebut>2018-02-14</dateDebut>
      <datePublication xsi:nil="true"/>
      <dateFin>2020-12-17</dateFin>
      <preseance>10</preseance>
      <nominPrincipale>1</nominPrincipale>
      <infosQualite>
        <codeQualite>Membre</codeQualite>
        <libQualite>Membre</libQualite>
        <libQualiteSex>Membre</libQualiteSex>
      </infosQualite>
      <organes>
        <organeRef>PO750141</organeRef>
      </organes>
      <libelle xsi:nil="true"/>
      <missionSuivanteRef xsi:nil="true"/>
      <missionPrecedenteRef xsi:nil="true"/>
    </mandat>
    <mandat xmlns:xsi="http://www.w3.org/2001/XMLSchema-instance" xsi:type="MandatSimple_Type">
      <uid>PM779174</uid>
      <acteurRef>PA721262</acteurRef>
      <legislature>15</legislature>
      <typeOrgane>CNPS</typeOrgane>
      <dateDebut>2020-12-13</dateDebut>
      <datePublication>2020-12-13</datePublication>
      <dateFin>2021-08-24</dateFin>
      <preseance>20</preseance>
      <nominPrincipale>1</nominPrincipale>
      <infosQualite>
        <codeQualite>Membre</codeQualite>
        <libQualite>Membre</libQualite>
        <libQualiteSex>Membre</libQualiteSex>
      </infosQualite>
      <organes>
        <organeRef>PO779099</organeRef>
      </organes>
    </mandat>
    <mandat xmlns:xsi="http://www.w3.org/2001/XMLSchema-instance" xsi:type="MandatSimple_Type">
      <uid>PM782960</uid>
      <acteurRef>PA721262</acteurRef>
      <legislature>15</legislature>
      <typeOrgane>CNPS</typeOrgane>
      <dateDebut>2021-05-08</dateDebut>
      <datePublication>2021-05-08</datePublication>
      <dateFin>2022-02-09</dateFin>
      <preseance>20</preseance>
      <nominPrincipale>1</nominPrincipale>
      <infosQualite>
        <codeQualite>Membre</codeQualite>
        <libQualite>Membre</libQualite>
        <libQualiteSex>Membre</libQualiteSex>
      </infosQualite>
      <organes>
        <organeRef>PO782816</organeRef>
      </organes>
    </mandat>
    <mandat xmlns:xsi="http://www.w3.org/2001/XMLSchema-instance" xsi:type="MandatSimple_Type">
      <uid>PM766809</uid>
      <acteurRef>PA721262</acteurRef>
      <legislature>15</legislature>
      <typeOrgane>CNPS</typeOrgane>
      <dateDebut>2019-07-24</dateDebut>
      <datePublication>2019-07-25</datePublication>
      <dateFin>2021-08-02</dateFin>
      <preseance>20</preseance>
      <nominPrincipale>1</nominPrincipale>
      <infosQualite>
        <codeQualite>Membre</codeQualite>
        <libQualite>Membre</libQualite>
        <libQualiteSex>Membre</libQualiteSex>
      </infosQualite>
      <organes>
        <organeRef>PO766718</organeRef>
      </organes>
    </mandat>
    <mandat xmlns:xsi="http://www.w3.org/2001/XMLSchema-instance" xsi:type="MandatSimple_Type">
      <uid>PM769165</uid>
      <acteurRef>PA721262</acteurRef>
      <legislature>15</legislature>
      <typeOrgane>CNPE</typeOrgane>
      <dateDebut>2020-01-14</dateDebut>
      <datePublication>2020-01-15</datePublication>
      <dateFin>2020-09-02</dateFin>
      <preseance>20</preseance>
      <nominPrincipale>1</nominPrincipale>
      <infosQualite>
        <codeQualite>Membre</codeQualite>
        <libQualite>Membre</libQualite>
        <libQualiteSex>Membre</libQualiteSex>
      </infosQualite>
      <organes>
        <organeRef>PO769010</organeRef>
      </organes>
    </mandat>
    <mandat xmlns:xsi="http://www.w3.org/2001/XMLSchema-instance" xsi:type="MandatSimple_Type">
      <uid>PM781489</uid>
      <acteurRef>PA721262</acteurRef>
      <legislature>15</legislature>
      <typeOrgane>CNPE</typeOrgane>
      <dateDebut>2021-02-19</dateDebut>
      <datePublication>2021-02-19</datePublication>
      <dateFin>2021-07-15</dateFin>
      <preseance>20</preseance>
      <nominPrincipale>1</nominPrincipale>
      <infosQualite>
        <codeQualite>Membre</codeQualite>
        <libQualite>Membre</libQualite>
        <libQualiteSex>Membre</libQualiteSex>
      </infosQualite>
      <organes>
        <organeRef>PO780709</organeRef>
      </organes>
    </mandat>
    <mandat xmlns:xsi="http://www.w3.org/2001/XMLSchema-instance" xsi:type="MandatSimple_Type">
      <uid>PM780832</uid>
      <acteurRef>PA721262</acteurRef>
      <legislature>15</legislature>
      <typeOrgane>CNPE</typeOrgane>
      <dateDebut>2021-02-10</dateDebut>
      <datePublication>2021-02-11</datePublication>
      <dateFin>2021-07-21</dateFin>
      <preseance>20</preseance>
      <nominPrincipale>1</nominPrincipale>
      <infosQualite>
        <codeQualite>Membre</codeQualite>
        <libQualite>Membre</libQualite>
        <libQualiteSex>Membre</libQualiteSex>
      </infosQualite>
      <organes>
        <organeRef>PO780290</organeRef>
      </organes>
    </mandat>
    <mandat xmlns:xsi="http://www.w3.org/2001/XMLSchema-instance" xsi:type="MandatSimple_Type">
      <uid>PM765749</uid>
      <acteurRef>PA721262</acteurRef>
      <legislature>15</legislature>
      <typeOrgane>CNPE</typeOrgane>
      <dateDebut>2019-06-13</dateDebut>
      <datePublication>2019-06-14</datePublication>
      <dateFin>2019-11-26</dateFin>
      <preseance>20</preseance>
      <nominPrincipale>1</nominPrincipale>
      <infosQualite>
        <codeQualite>Membre</codeQualite>
        <libQualite>Membre</libQualite>
        <libQualiteSex>Membre</libQualiteSex>
      </infosQualite>
      <organes>
        <organeRef>PO765498</organeRef>
      </organes>
    </mandat>
    <mandat xmlns:xsi="http://www.w3.org/2001/XMLSchema-instance" xsi:type="MandatSimple_Type">
      <uid>PM767619</uid>
      <acteurRef>PA721262</acteurRef>
      <legislature>15</legislature>
      <typeOrgane>CNPE</typeOrgane>
      <dateDebut>2019-10-18</dateDebut>
      <datePublication>2019-10-19</datePublication>
      <dateFin>2020-06-10</dateFin>
      <preseance>20</preseance>
      <nominPrincipale>1</nominPrincipale>
      <infosQualite>
        <codeQualite>Membre</codeQualite>
        <libQualite>Membre</libQualite>
        <libQualiteSex>Membre</libQualiteSex>
      </infosQualite>
      <organes>
        <organeRef>PO767517</organeRef>
      </organes>
    </mandat>
    <mandat xmlns:xsi="http://www.w3.org/2001/XMLSchema-instance" xsi:type="MandatSimple_Type">
      <uid>PM757081</uid>
      <acteurRef>PA721262</acteurRef>
      <legislature>15</legislature>
      <typeOrgane>ORGEXTPARL</typeOrgane>
      <dateDebut>2018-06-04</dateDebut>
      <datePublication>2018-06-05</datePublication>
      <dateFin xsi:nil="true"/>
      <preseance>20</preseance>
      <nominPrincipale>1</nominPrincipale>
      <infosQualite>
        <codeQualite>Titulaire</codeQualite>
        <libQualite>Membre titulaire</libQualite>
        <libQualiteSex>Membre titulaire</libQualiteSex>
      </infosQualite>
      <organes>
        <organeRef>PO756933</organeRef>
      </organes>
    </mandat>
    <mandat xmlns:xsi="http://www.w3.org/2001/XMLSchema-instance" xsi:type="MandatSimple_Type">
      <uid>PM763480</uid>
      <acteurRef>PA721262</acteurRef>
      <legislature>15</legislature>
      <typeOrgane>ORGEXTPARL</typeOrgane>
      <dateDebut>2019-03-14</dateDebut>
      <datePublication>2019-03-15</datePublication>
      <dateFin xsi:nil="true"/>
      <preseance>20</preseance>
      <nominPrincipale>1</nominPrincipale>
      <infosQualite>
        <codeQualite>Titulaire</codeQualite>
        <libQualite>Membre titulaire</libQualite>
        <libQualiteSex>Membre titulaire</libQualiteSex>
      </infosQualite>
      <organes>
        <organeRef>PO763346</organeRef>
      </organes>
    </mandat>
    <mandat xmlns:xsi="http://www.w3.org/2001/XMLSchema-instance" xsi:type="MandatSimple_Type">
      <uid>PM738071</uid>
      <acteurRef>PA721262</acteurRef>
      <legislature>15</legislature>
      <typeOrgane>ORGEXTPARL</typeOrgane>
      <dateDebut>2017-10-05</dateDebut>
      <datePublication>2017-10-06</datePublication>
      <dateFin xsi:nil="true"/>
      <preseance>20</preseance>
      <nominPrincipale>1</nominPrincipale>
      <infosQualite>
        <codeQualite>Titulaire</codeQualite>
        <libQualite>Membre titulaire</libQualite>
        <libQualiteSex>Membre titulaire</libQualiteSex>
      </infosQualite>
      <organes>
        <organeRef>PO60291</organeRef>
      </organes>
    </mandat>
    <mandat xmlns:xsi="http://www.w3.org/2001/XMLSchema-instance" xsi:type="MandatSimple_Type">
      <uid>PM747995</uid>
      <acteurRef>PA721262</acteurRef>
      <legislature>15</legislature>
      <typeOrgane>ORGEXTPARL</typeOrgane>
      <dateDebut>2018-01-10</dateDebut>
      <datePublication>2018-01-11</datePublication>
      <dateFin xsi:nil="true"/>
      <preseance>20</preseance>
      <nominPrincipale>1</nominPrincipale>
      <infosQualite>
        <codeQualite>Titulaire</codeQualite>
        <libQualite>Membre titulaire</libQualite>
        <libQualiteSex>Membre titulaire</libQualiteSex>
      </infosQualite>
      <organes>
        <organeRef>PO717436</organeRef>
      </organes>
    </mandat>
    <mandat xmlns:xsi="http://www.w3.org/2001/XMLSchema-instance" xsi:type="MandatSimple_Type">
      <uid>PM731189</uid>
      <acteurRef>PA721262</acteurRef>
      <legislature>15</legislature>
      <typeOrgane>GP</typeOrgane>
      <dateDebut>2017-06-27</dateDebut>
      <datePublication>2017-06-28</datePublication>
      <dateFin xsi:nil="true"/>
      <preseance>20</preseance>
      <nominPrincipale>1</nominPrincipale>
      <infosQualite>
        <codeQualite>Membre</codeQualite>
        <libQualite>Membre du</libQualite>
        <libQualiteSex>Membre du</libQualiteSex>
      </infosQualite>
      <organes>
        <organeRef>PO730964</organeRef>
      </organes>
    </mandat>
    <mandat xmlns:xsi="http://www.w3.org/2001/XMLSchema-instance" xsi:type="MandatMission_Type">
      <uid>PM742880</uid>
      <acteurRef>PA721262</acteurRef>
      <legislature>15</legislature>
      <typeOrgane>MISINFOCOM</typeOrgane>
      <dateDebut>2017-11-09</dateDebut>
      <datePublication xsi:nil="true"/>
      <dateFin>2018-05-31</dateFin>
      <preseance>16</preseance>
      <nominPrincipale>1</nominPrincipale>
      <infosQualite>
        <codeQualite>Rapporteur</codeQualite>
        <libQualite>Rapporteur</libQualite>
        <libQualiteSex>Rapporteur</libQualiteSex>
      </infosQualite>
      <organes>
        <organeRef>PO742386</organeRef>
      </organes>
      <libelle xsi:nil="true"/>
      <missionSuivanteRef xsi:nil="true"/>
      <missionPrecedenteRef xsi:nil="true"/>
    </mandat>
    <mandat xmlns:xsi="http://www.w3.org/2001/XMLSchema-instance" xsi:type="MandatSimple_Type">
      <uid>PM731893</uid>
      <acteurRef>PA721262</acteurRef>
      <legislature>15</legislature>
      <typeOrgane>COMPER</typeOrgane>
      <dateDebut>2017-06-29</dateDebut>
      <datePublication>2017-06-29</datePublication>
      <dateFin>2021-01-19</dateFin>
      <preseance>32</preseance>
      <nominPrincipale>1</nominPrincipale>
      <infosQualite>
        <codeQualite>Membre</codeQualite>
        <libQualite>Membre</libQualite>
        <libQualiteSex>Membre</libQualiteSex>
      </infosQualite>
      <organes>
        <organeRef>PO59051</organeRef>
      </organes>
    </mandat>
    <mandat xmlns:xsi="http://www.w3.org/2001/XMLSchema-instance" xsi:type="MandatSimple_Type">
      <uid>PM779818</uid>
      <acteurRef>PA721262</acteurRef>
      <legislature>15</legislature>
      <typeOrgane>COMPER</typeOrgane>
      <dateDebut>2021-01-21</dateDebut>
      <datePublication>2021-01-21</datePublication>
      <dateFin>2021-06-04</dateFin>
      <preseance>32</preseance>
      <nominPrincipale>1</nominPrincipale>
      <infosQualite>
        <codeQualite>Membre</codeQualite>
        <libQualite>Membre</libQualite>
        <libQualiteSex>Membre</libQualiteSex>
      </infosQualite>
      <organes>
        <organeRef>PO59051</organeRef>
      </organes>
    </mandat>
    <mandat xmlns:xsi="http://www.w3.org/2001/XMLSchema-instance" xsi:type="MandatSimple_Type">
      <uid>PM779794</uid>
      <acteurRef>PA721262</acteurRef>
      <legislature>15</legislature>
      <typeOrgane>COMPER</typeOrgane>
      <dateDebut>2021-01-20</dateDebut>
      <datePublication>2021-01-20</datePublication>
      <dateFin>2021-01-20</dateFin>
      <preseance>32</preseance>
      <nominPrincipale>1</nominPrincipale>
      <infosQualite>
        <codeQualite>Membre</codeQualite>
        <libQualite>Membre</libQualite>
        <libQualiteSex>Membre</libQualiteSex>
      </infosQualite>
      <organes>
        <organeRef>PO59048</organeRef>
      </organes>
    </mandat>
    <mandat xmlns:xsi="http://www.w3.org/2001/XMLSchema-instance" xsi:type="MandatSimple_Type">
      <uid>PM783440</uid>
      <acteurRef>PA721262</acteurRef>
      <legislature>15</legislature>
      <typeOrgane>COMPER</typeOrgane>
      <dateDebut>2021-06-05</dateDebut>
      <datePublication>2021-06-05</datePublication>
      <dateFin>2021-06-09</dateFin>
      <preseance>32</preseance>
      <nominPrincipale>1</nominPrincipale>
      <infosQualite>
        <codeQualite>Membre</codeQualite>
        <libQualite>Membre</libQualite>
        <libQualiteSex>Membre</libQualiteSex>
      </infosQualite>
      <organes>
        <organeRef>PO59046</organeRef>
      </organes>
    </mandat>
    <mandat xmlns:xsi="http://www.w3.org/2001/XMLSchema-instance" xsi:type="MandatSimple_Type">
      <uid>PM783649</uid>
      <acteurRef>PA721262</acteurRef>
      <legislature>15</legislature>
      <typeOrgane>COMPER</typeOrgane>
      <dateDebut>2021-06-10</dateDebut>
      <datePublication>2021-06-10</datePublication>
      <dateFin xsi:nil="true"/>
      <preseance>32</preseance>
      <nominPrincipale>1</nominPrincipale>
      <infosQualite>
        <codeQualite>Membre</codeQualite>
        <libQualite>Membre</libQualite>
        <libQualiteSex>Membre</libQualiteSex>
      </infosQualite>
      <organes>
        <organeRef>PO59051</organeRef>
      </organes>
    </mandat>
    <mandat xmlns:xsi="http://www.w3.org/2001/XMLSchema-instance" xsi:type="MandatSimple_Type">
      <uid>PM772461</uid>
      <acteurRef>PA721262</acteurRef>
      <legislature>15</legislature>
      <typeOrgane>CMP</typeOrgane>
      <dateDebut>2020-06-12</dateDebut>
      <datePublication>2020-06-13</datePublication>
      <dateFin>2020-06-17</dateFin>
      <preseance>20</preseance>
      <nominPrincipale>1</nominPrincipale>
      <infosQualite>
        <codeQualite>Titulaire</codeQualite>
        <libQualite>Membre titulaire</libQualite>
        <libQualiteSex>Membre titulaire</libQualiteSex>
      </infosQualite>
      <organes>
        <organeRef>PO772430</organeRef>
      </organes>
    </mandat>
    <mandat xmlns:xsi="http://www.w3.org/2001/XMLSchema-instance" xsi:type="MandatSimple_Type">
      <uid>PM772638</uid>
      <acteurRef>PA721262</acteurRef>
      <legislature>15</legislature>
      <typeOrgane>CMP</typeOrgane>
      <dateDebut>2020-06-15</dateDebut>
      <datePublication>2020-06-16</datePublication>
      <dateFin>2020-06-17</dateFin>
      <preseance>16</preseance>
      <nominPrincipale>1</nominPrincipale>
      <infosQualite>
        <codeQualite>Rapporteur</codeQualite>
        <libQualite>Rapporteur</libQualite>
        <libQualiteSex>Rapporteur</libQualiteSex>
      </infosQualite>
      <organes>
        <organeRef>PO772430</organeRef>
      </organes>
    </mandat>
    <mandat xmlns:xsi="http://www.w3.org/2001/XMLSchema-instance" xsi:type="MandatSimple_Type">
      <uid>PM773962</uid>
      <acteurRef>PA721262</acteurRef>
      <legislature>15</legislature>
      <typeOrgane>CMP</typeOrgane>
      <dateDebut>2020-07-16</dateDebut>
      <datePublication>2020-07-22</datePublication>
      <dateFin>2020-07-27</dateFin>
      <preseance>20</preseance>
      <nominPrincipale>1</nominPrincipale>
      <infosQualite>
        <codeQualite>Titulaire</codeQualite>
        <libQualite>Membre titulaire</libQualite>
        <libQualiteSex>Membre titulaire</libQualiteSex>
      </infosQualite>
      <organes>
        <organeRef>PO773832</organeRef>
      </organes>
    </mandat>
    <mandat xmlns:xsi="http://www.w3.org/2001/XMLSchema-instance" xsi:type="MandatSimple_Type">
      <uid>PM764981</uid>
      <acteurRef>PA721262</acteurRef>
      <legislature>15</legislature>
      <typeOrgane>CMP</typeOrgane>
      <dateDebut>2019-05-07</dateDebut>
      <datePublication>2019-05-08</datePublication>
      <dateFin>2019-05-23</dateFin>
      <preseance>16</preseance>
      <nominPrincipale>1</nominPrincipale>
      <infosQualite>
        <codeQualite>Rapporteur</codeQualite>
        <libQualite>Rapporteur</libQualite>
        <libQualiteSex>Rapporteur</libQualiteSex>
      </infosQualite>
      <organes>
        <organeRef>PO764697</organeRef>
      </organes>
    </mandat>
    <mandat xmlns:xsi="http://www.w3.org/2001/XMLSchema-instance" xsi:type="MandatSimple_Type">
      <uid>PM764985</uid>
      <acteurRef>PA721262</acteurRef>
      <legislature>15</legislature>
      <typeOrgane>CMP</typeOrgane>
      <dateDebut>2019-05-07</dateDebut>
      <datePublication>2019-05-08</datePublication>
      <dateFin>2019-05-23</dateFin>
      <preseance>16</preseance>
      <nominPrincipale>1</nominPrincipale>
      <infosQualite>
        <codeQualite>Rapporteur</codeQualite>
        <libQualite>Rapporteur</libQualite>
        <libQualiteSex>Rapporteur</libQualiteSex>
      </infosQualite>
      <organes>
        <organeRef>PO764703</organeRef>
      </organes>
    </mandat>
    <mandat xmlns:xsi="http://www.w3.org/2001/XMLSchema-instance" xsi:type="MandatSimple_Type">
      <uid>PM764850</uid>
      <acteurRef>PA721262</acteurRef>
      <legislature>15</legislature>
      <typeOrgane>CMP</typeOrgane>
      <dateDebut>2019-04-30</dateDebut>
      <datePublication>2019-05-02</datePublication>
      <dateFin>2019-05-23</dateFin>
      <preseance>20</preseance>
      <nominPrincipale>1</nominPrincipale>
      <infosQualite>
        <codeQualite>Titulaire</codeQualite>
        <libQualite>Membre titulaire</libQualite>
        <libQualiteSex>Membre titulaire</libQualiteSex>
      </infosQualite>
      <organes>
        <organeRef>PO764697</organeRef>
      </organes>
    </mandat>
    <mandat xmlns:xsi="http://www.w3.org/2001/XMLSchema-instance" xsi:type="MandatSimple_Type">
      <uid>PM771584</uid>
      <acteurRef>PA721262</acteurRef>
      <legislature>15</legislature>
      <typeOrgane>CMP</typeOrgane>
      <dateDebut>2020-05-06</dateDebut>
      <datePublication>2020-05-07</datePublication>
      <dateFin>2020-05-12</dateFin>
      <preseance>20</preseance>
      <nominPrincipale>1</nominPrincipale>
      <infosQualite>
        <codeQualite>Titulaire</codeQualite>
        <libQualite>Membre titulaire</libQualite>
        <libQualiteSex>Membre titulaire</libQualiteSex>
      </infosQualite>
      <organes>
        <organeRef>PO771574</organeRef>
      </organes>
    </mandat>
    <mandat xmlns:xsi="http://www.w3.org/2001/XMLSchema-instance" xsi:type="MandatSimple_Type">
      <uid>PM766065</uid>
      <acteurRef>PA721262</acteurRef>
      <legislature>15</legislature>
      <typeOrgane>CMP</typeOrgane>
      <dateDebut>2019-06-27</dateDebut>
      <datePublication>2019-06-28</datePublication>
      <dateFin>2019-07-24</dateFin>
      <preseance>20</preseance>
      <nominPrincipale>1</nominPrincipale>
      <infosQualite>
        <codeQualite>Titulaire</codeQualite>
        <libQualite>Membre titulaire</libQualite>
        <libQualiteSex>Membre titulaire</libQualiteSex>
      </infosQualite>
      <organes>
        <organeRef>PO766053</organeRef>
      </organes>
    </mandat>
    <mandat xmlns:xsi="http://www.w3.org/2001/XMLSchema-instance" xsi:type="MandatSimple_Type">
      <uid>PM768388</uid>
      <acteurRef>PA721262</acteurRef>
      <legislature>15</legislature>
      <typeOrgane>CMP</typeOrgane>
      <dateDebut>2019-11-21</dateDebut>
      <datePublication>2019-11-22</datePublication>
      <dateFin>2019-12-18</dateFin>
      <preseance>20</preseance>
      <nominPrincipale>1</nominPrincipale>
      <infosQualite>
        <codeQualite>Titulaire</codeQualite>
        <libQualite>Membre titulaire</libQualite>
        <libQualiteSex>Membre titulaire</libQualiteSex>
      </infosQualite>
      <organes>
        <organeRef>PO768135</organeRef>
      </organes>
    </mandat>
    <mandat xmlns:xsi="http://www.w3.org/2001/XMLSchema-instance" xsi:type="MandatSimple_Type">
      <uid>PM769728</uid>
      <acteurRef>PA721262</acteurRef>
      <legislature>15</legislature>
      <typeOrgane>CMP</typeOrgane>
      <dateDebut>2020-01-23</dateDebut>
      <datePublication>2020-01-29</datePublication>
      <dateFin>2020-03-31</dateFin>
      <preseance>20</preseance>
      <nominPrincipale>1</nominPrincipale>
      <infosQualite>
        <codeQualite>Titulaire</codeQualite>
        <libQualite>Membre titulaire</libQualite>
        <libQualiteSex>Membre titulaire</libQualiteSex>
      </infosQualite>
      <organes>
        <organeRef>PO769520</organeRef>
      </organes>
    </mandat>
    <mandat xmlns:xsi="http://www.w3.org/2001/XMLSchema-instance" xsi:type="MandatSimple_Type">
      <uid>PM766248</uid>
      <acteurRef>PA721262</acteurRef>
      <legislature>15</legislature>
      <typeOrgane>CMP</typeOrgane>
      <dateDebut>2019-07-04</dateDebut>
      <datePublication>2019-07-05</datePublication>
      <dateFin>2019-07-25</dateFin>
      <preseance>20</preseance>
      <nominPrincipale>1</nominPrincipale>
      <infosQualite>
        <codeQualite>Titulaire</codeQualite>
        <libQualite>Membre titulaire</libQualite>
        <libQualiteSex>Membre titulaire</libQualiteSex>
      </infosQualite>
      <organes>
        <organeRef>PO766090</organeRef>
      </organes>
    </mandat>
    <mandat xmlns:xsi="http://www.w3.org/2001/XMLSchema-instance" xsi:type="MandatSimple_Type">
      <uid>PM768607</uid>
      <acteurRef>PA721262</acteurRef>
      <legislature>15</legislature>
      <typeOrgane>CMP</typeOrgane>
      <dateDebut>2019-12-04</dateDebut>
      <datePublication>2019-12-05</datePublication>
      <dateFin>2019-12-19</dateFin>
      <preseance>20</preseance>
      <nominPrincipale>1</nominPrincipale>
      <infosQualite>
        <codeQualite>Titulaire</codeQualite>
        <libQualite>Membre titulaire</libQualite>
        <libQualiteSex>Membre titulaire</libQualiteSex>
      </infosQualite>
      <organes>
        <organeRef>PO768530</organeRef>
      </organes>
    </mandat>
    <mandat xmlns:xsi="http://www.w3.org/2001/XMLSchema-instance" xsi:type="MandatSimple_Type">
      <uid>PM769701</uid>
      <acteurRef>PA721262</acteurRef>
      <legislature>15</legislature>
      <typeOrgane>CMP</typeOrgane>
      <dateDebut>2020-01-23</dateDebut>
      <datePublication>2020-01-29</datePublication>
      <dateFin>2020-03-31</dateFin>
      <preseance>20</preseance>
      <nominPrincipale>1</nominPrincipale>
      <infosQualite>
        <codeQualite>Titulaire</codeQualite>
        <libQualite>Membre titulaire</libQualite>
        <libQualiteSex>Membre titulaire</libQualiteSex>
      </infosQualite>
      <organes>
        <organeRef>PO769513</organeRef>
      </organes>
    </mandat>
    <mandat xmlns:xsi="http://www.w3.org/2001/XMLSchema-instance" xsi:type="MandatSimple_Type">
      <uid>PM789392</uid>
      <acteurRef>PA721262</acteurRef>
      <legislature>15</legislature>
      <typeOrgane>CMP</typeOrgane>
      <dateDebut>2022-01-28</dateDebut>
      <datePublication>2022-01-29</datePublication>
      <dateFin>2022-02-17</dateFin>
      <preseance>20</preseance>
      <nominPrincipale>1</nominPrincipale>
      <infosQualite>
        <codeQualite>Titulaire</codeQualite>
        <libQualite>Membre titulaire</libQualite>
        <libQualiteSex>Membre titulaire</libQualiteSex>
      </infosQualite>
      <organes>
        <organeRef>PO789339</organeRef>
      </organes>
    </mandat>
    <mandat xmlns:xsi="http://www.w3.org/2001/XMLSchema-instance" xsi:type="MandatSimple_Type">
      <uid>PM768902</uid>
      <acteurRef>PA721262</acteurRef>
      <legislature>15</legislature>
      <typeOrgane>CMP</typeOrgane>
      <dateDebut>2019-12-19</dateDebut>
      <datePublication>2019-12-20</datePublication>
      <dateFin>2020-05-13</dateFin>
      <preseance>20</preseance>
      <nominPrincipale>1</nominPrincipale>
      <infosQualite>
        <codeQualite>Titulaire</codeQualite>
        <libQualite>Membre titulaire</libQualite>
        <libQualiteSex>Membre titulaire</libQualiteSex>
      </infosQualite>
      <organes>
        <organeRef>PO768870</organeRef>
      </organes>
    </mandat>
    <mandat xmlns:xsi="http://www.w3.org/2001/XMLSchema-instance" xsi:type="MandatSimple_Type">
      <uid>PM782873</uid>
      <acteurRef>PA721262</acteurRef>
      <legislature>15</legislature>
      <typeOrgane>CMP</typeOrgane>
      <dateDebut>2021-05-06</dateDebut>
      <datePublication>2021-05-07</datePublication>
      <dateFin>2021-07-23</dateFin>
      <preseance>20</preseance>
      <nominPrincipale>1</nominPrincipale>
      <infosQualite>
        <codeQualite>Titulaire</codeQualite>
        <libQualite>Membre titulaire</libQualite>
        <libQualiteSex>Membre titulaire</libQualiteSex>
      </infosQualite>
      <organes>
        <organeRef>PO782491</organeRef>
      </organes>
    </mandat>
    <mandat xmlns:xsi="http://www.w3.org/2001/XMLSchema-instance" xsi:type="MandatSimple_Type">
      <uid>PM764829</uid>
      <acteurRef>PA721262</acteurRef>
      <legislature>15</legislature>
      <typeOrgane>CMP</typeOrgane>
      <dateDebut>2019-04-30</dateDebut>
      <datePublication>2019-05-02</datePublication>
      <dateFin>2019-05-23</dateFin>
      <preseance>20</preseance>
      <nominPrincipale>1</nominPrincipale>
      <infosQualite>
        <codeQualite>Titulaire</codeQualite>
        <libQualite>Membre titulaire</libQualite>
        <libQualiteSex>Membre titulaire</libQualiteSex>
      </infosQualite>
      <organes>
        <organeRef>PO764703</organeRef>
      </organes>
    </mandat>
    <mandat xmlns:xsi="http://www.w3.org/2001/XMLSchema-instance" xsi:type="MandatSimple_Type">
      <uid>PM783189</uid>
      <acteurRef>PA721262</acteurRef>
      <legislature>15</legislature>
      <typeOrgane>CMP</typeOrgane>
      <dateDebut>2021-05-18</dateDebut>
      <datePublication>2021-05-19</datePublication>
      <dateFin>2021-05-27</dateFin>
      <preseance>20</preseance>
      <nominPrincipale>1</nominPrincipale>
      <infosQualite>
        <codeQualite>Titulaire</codeQualite>
        <libQualite>Membre titulaire</libQualite>
        <libQualiteSex>Membre titulaire</libQualiteSex>
      </infosQualite>
      <organes>
        <organeRef>PO783142</organeRef>
      </organes>
    </mandat>
    <mandat xmlns:xsi="http://www.w3.org/2001/XMLSchema-instance" xsi:type="MandatSimple_Type">
      <uid>PM772809</uid>
      <acteurRef>PA721262</acteurRef>
      <legislature>15</legislature>
      <typeOrgane>CMP</typeOrgane>
      <dateDebut>2020-06-23</dateDebut>
      <datePublication>2020-06-24</datePublication>
      <dateFin>2020-07-02</dateFin>
      <preseance>20</preseance>
      <nominPrincipale>1</nominPrincipale>
      <infosQualite>
        <codeQualite>Titulaire</codeQualite>
        <libQualite>Membre titulaire</libQualite>
        <libQualiteSex>Membre titulaire</libQualiteSex>
      </infosQualite>
      <organes>
        <organeRef>PO772795</organeRef>
      </organes>
    </mandat>
    <mandat xmlns:xsi="http://www.w3.org/2001/XMLSchema-instance" xsi:type="MandatSimple_Type">
      <uid>PM754884</uid>
      <acteurRef>PA721262</acteurRef>
      <legislature>15</legislature>
      <typeOrgane>GE</typeOrgane>
      <dateDebut>2018-03-02</dateDebut>
      <datePublication xsi:nil="true"/>
      <dateFin xsi:nil="true"/>
      <preseance>20</preseance>
      <nominPrincipale>1</nominPrincipale>
      <infosQualite>
        <codeQualite>Membre</codeQualite>
        <libQualite>Membre</libQualite>
        <libQualiteSex>Membre</libQualiteSex>
      </infosQualite>
      <organes>
        <organeRef>PO746852</organeRef>
      </organes>
    </mandat>
    <mandat xmlns:xsi="http://www.w3.org/2001/XMLSchema-instance" xsi:type="MandatSimple_Type">
      <uid>PM754387</uid>
      <acteurRef>PA721262</acteurRef>
      <legislature>15</legislature>
      <typeOrgane>GE</typeOrgane>
      <dateDebut>2018-03-27</dateDebut>
      <datePublication xsi:nil="true"/>
      <dateFin xsi:nil="true"/>
      <preseance>12</preseance>
      <nominPrincipale>1</nominPrincipale>
      <infosQualite>
        <codeQualite>Secrétaire</codeQualite>
        <libQualite>Secrétaire</libQualite>
        <libQualiteSex>Secrétaire</libQualiteSex>
      </infosQualite>
      <organes>
        <organeRef>PO746629</organeRef>
      </organes>
    </mandat>
    <mandat xmlns:xsi="http://www.w3.org/2001/XMLSchema-instance" xsi:type="MandatSimple_Type">
      <uid>PM765217</uid>
      <acteurRef>PA721262</acteurRef>
      <legislature>15</legislature>
      <typeOrgane>GE</typeOrgane>
      <dateDebut>2019-05-15</dateDebut>
      <datePublication xsi:nil="true"/>
      <dateFin xsi:nil="true"/>
      <preseance>20</preseance>
      <nominPrincipale>0</nominPrincipale>
      <infosQualite>
        <codeQualite>Membre</codeQualite>
        <libQualite>Membre</libQualite>
        <libQualiteSex>Membre</libQualiteSex>
      </infosQualite>
      <organes>
        <organeRef>PO763229</organeRef>
      </organes>
    </mandat>
    <mandat xmlns:xsi="http://www.w3.org/2001/XMLSchema-instance" xsi:type="MandatSimple_Type">
      <uid>PM750767</uid>
      <acteurRef>PA721262</acteurRef>
      <legislature>15</legislature>
      <typeOrgane>GE</typeOrgane>
      <dateDebut>2018-02-16</dateDebut>
      <datePublication xsi:nil="true"/>
      <dateFin xsi:nil="true"/>
      <preseance>20</preseance>
      <nominPrincipale>1</nominPrincipale>
      <infosQualite>
        <codeQualite>Membre</codeQualite>
        <libQualite>Membre</libQualite>
        <libQualiteSex>Membre</libQualiteSex>
      </infosQualite>
      <organes>
        <organeRef>PO747170</organeRef>
      </organes>
    </mandat>
    <mandat xmlns:xsi="http://www.w3.org/2001/XMLSchema-instance" xsi:type="MandatSimple_Type">
      <uid>PM751470</uid>
      <acteurRef>PA721262</acteurRef>
      <legislature>15</legislature>
      <typeOrgane>GE</typeOrgane>
      <dateDebut>2018-02-21</dateDebut>
      <datePublication xsi:nil="true"/>
      <dateFin xsi:nil="true"/>
      <preseance>20</preseance>
      <nominPrincipale>1</nominPrincipale>
      <infosQualite>
        <codeQualite>Membre</codeQualite>
        <libQualite>Membre</libQualite>
        <libQualiteSex>Membre</libQualiteSex>
      </infosQualite>
      <organes>
        <organeRef>PO746857</organeRef>
      </organes>
    </mandat>
    <mandat xmlns:xsi="http://www.w3.org/2001/XMLSchema-instance" xsi:type="MandatSimple_Type">
      <uid>PM754102</uid>
      <acteurRef>PA721262</acteurRef>
      <legislature>15</legislature>
      <typeOrgane>GE</typeOrgane>
      <dateDebut>2018-03-21</dateDebut>
      <datePublication xsi:nil="true"/>
      <dateFin>2020-01-15</dateFin>
      <preseance>20</preseance>
      <nominPrincipale>1</nominPrincipale>
      <infosQualite>
        <codeQualite>Membre</codeQualite>
        <libQualite>Membre</libQualite>
        <libQualiteSex>Membre</libQualiteSex>
      </infosQualite>
      <organes>
        <organeRef>PO747124</organeRef>
      </organes>
    </mandat>
    <mandat xmlns:xsi="http://www.w3.org/2001/XMLSchema-instance" xsi:type="MandatSimple_Type">
      <uid>PM750750</uid>
      <acteurRef>PA721262</acteurRef>
      <legislature>15</legislature>
      <typeOrgane>GE</typeOrgane>
      <dateDebut>2018-02-16</dateDebut>
      <datePublication xsi:nil="true"/>
      <dateFin xsi:nil="true"/>
      <preseance>20</preseance>
      <nominPrincipale>1</nominPrincipale>
      <infosQualite>
        <codeQualite>Membre</codeQualite>
        <libQualite>Membre</libQualite>
        <libQualiteSex>Membre</libQualiteSex>
      </infosQualite>
      <organes>
        <organeRef>PO746847</organeRef>
      </organes>
    </mandat>
    <mandat xmlns:xsi="http://www.w3.org/2001/XMLSchema-instance" xsi:type="MandatSimple_Type">
      <uid>PM751384</uid>
      <acteurRef>PA721262</acteurRef>
      <legislature>15</legislature>
      <typeOrgane>GE</typeOrgane>
      <dateDebut>2018-03-13</dateDebut>
      <datePublication xsi:nil="true"/>
      <dateFin xsi:nil="true"/>
      <preseance>20</preseance>
      <nominPrincipale>1</nominPrincipale>
      <infosQualite>
        <codeQualite>Membre</codeQualite>
        <libQualite>Membre</libQualite>
        <libQualiteSex>Membre</libQualiteSex>
      </infosQualite>
      <organes>
        <organeRef>PO746899</organeRef>
      </organes>
    </mandat>
    <mandat xmlns:xsi="http://www.w3.org/2001/XMLSchema-instance" xsi:type="MandatSimple_Type">
      <uid>PM750797</uid>
      <acteurRef>PA721262</acteurRef>
      <legislature>15</legislature>
      <typeOrgane>GE</typeOrgane>
      <dateDebut>2018-02-16</dateDebut>
      <datePublication xsi:nil="true"/>
      <dateFin xsi:nil="true"/>
      <preseance>20</preseance>
      <nominPrincipale>1</nominPrincipale>
      <infosQualite>
        <codeQualite>Membre</codeQualite>
        <libQualite>Membre</libQualite>
        <libQualiteSex>Membre</libQualiteSex>
      </infosQualite>
      <organes>
        <organeRef>PO747266</organeRef>
      </organes>
    </mandat>
    <mandat xmlns:xsi="http://www.w3.org/2001/XMLSchema-instance" xsi:type="MandatSimple_Type">
      <uid>PM750550</uid>
      <acteurRef>PA721262</acteurRef>
      <legislature>15</legislature>
      <typeOrgane>GE</typeOrgane>
      <dateDebut>2018-02-12</dateDebut>
      <datePublication xsi:nil="true"/>
      <dateFin xsi:nil="true"/>
      <preseance>20</preseance>
      <nominPrincipale>1</nominPrincipale>
      <infosQualite>
        <codeQualite>Membre</codeQualite>
        <libQualite>Membre</libQualite>
        <libQualiteSex>Membre</libQualiteSex>
      </infosQualite>
      <organes>
        <organeRef>PO746977</organeRef>
      </organes>
    </mandat>
    <mandat xmlns:xsi="http://www.w3.org/2001/XMLSchema-instance" xsi:type="MandatSimple_Type">
      <uid>PM752875</uid>
      <acteurRef>PA721262</acteurRef>
      <legislature>15</legislature>
      <typeOrgane>GE</typeOrgane>
      <dateDebut>2018-03-08</dateDebut>
      <datePublication xsi:nil="true"/>
      <dateFin xsi:nil="true"/>
      <preseance>20</preseance>
      <nominPrincipale>0</nominPrincipale>
      <infosQualite>
        <codeQualite>Membre</codeQualite>
        <libQualite>Membre</libQualite>
        <libQualiteSex>Membre</libQualiteSex>
      </infosQualite>
      <organes>
        <organeRef>PO746629</organeRef>
      </organes>
    </mandat>
    <mandat xmlns:xsi="http://www.w3.org/2001/XMLSchema-instance" xsi:type="MandatSimple_Type">
      <uid>PM724650</uid>
      <acteurRef>PA721262</acteurRef>
      <legislature>15</legislature>
      <typeOrgane>GP</typeOrgane>
      <dateDebut>2017-06-21</dateDebut>
      <datePublication xsi:nil="true"/>
      <dateFin>2017-06-26</dateFin>
      <preseance>28</preseance>
      <nominPrincipale>1</nominPrincipale>
      <infosQualite>
        <codeQualite>Député non-inscrit</codeQualite>
        <libQualite>Député non-inscrit</libQualite>
        <libQualiteSex>Député non-inscrit</libQualiteSex>
      </infosQualite>
      <organes>
        <organeRef>PO723569</organeRef>
      </organes>
    </mandat>
    <mandat xmlns:xsi="http://www.w3.org/2001/XMLSchema-instance" xsi:type="MandatSimple_Type">
      <uid>PM740735</uid>
      <acteurRef>PA721262</acteurRef>
      <legislature>15</legislature>
      <typeOrgane>GA</typeOrgane>
      <dateDebut>2017-10-24</dateDebut>
      <datePublication xsi:nil="true"/>
      <dateFin xsi:nil="true"/>
      <preseance>14</preseance>
      <nominPrincipale>1</nominPrincipale>
      <infosQualite>
        <codeQualite>Secrétaire</codeQualite>
        <libQualite>Secrétaire</libQualite>
        <libQualiteSex>Secrétaire</libQualiteSex>
      </infosQualite>
      <organes>
        <organeRef>PO733117</organeRef>
      </organes>
    </mandat>
    <mandat xmlns:xsi="http://www.w3.org/2001/XMLSchema-instance" xsi:type="MandatSimple_Type">
      <uid>PM764545</uid>
      <acteurRef>PA721262</acteurRef>
      <legislature>15</legislature>
      <typeOrgane>GA</typeOrgane>
      <dateDebut>2019-04-09</dateDebut>
      <datePublication xsi:nil="true"/>
      <dateFin xsi:nil="true"/>
      <preseance>20</preseance>
      <nominPrincipale>1</nominPrincipale>
      <infosQualite>
        <codeQualite>Membre</codeQualite>
        <libQualite>Membre</libQualite>
        <libQualiteSex>Membre</libQualiteSex>
      </infosQualite>
      <organes>
        <organeRef>PO733412</organeRef>
      </organes>
    </mandat>
    <mandat xmlns:xsi="http://www.w3.org/2001/XMLSchema-instance" xsi:type="MandatSimple_Type">
      <uid>PM739914</uid>
      <acteurRef>PA721262</acteurRef>
      <legislature>15</legislature>
      <typeOrgane>GA</typeOrgane>
      <dateDebut>2017-10-13</dateDebut>
      <datePublication xsi:nil="true"/>
      <dateFin xsi:nil="true"/>
      <preseance>20</preseance>
      <nominPrincipale>0</nominPrincipale>
      <infosQualite>
        <codeQualite>Membre</codeQualite>
        <libQualite>Membre</libQualite>
        <libQualiteSex>Membre</libQualiteSex>
      </infosQualite>
      <organes>
        <organeRef>PO732939</organeRef>
      </organes>
    </mandat>
    <mandat xmlns:xsi="http://www.w3.org/2001/XMLSchema-instance" xsi:type="MandatSimple_Type">
      <uid>PM739916</uid>
      <acteurRef>PA721262</acteurRef>
      <legislature>15</legislature>
      <typeOrgane>GA</typeOrgane>
      <dateDebut>2017-10-13</dateDebut>
      <datePublication xsi:nil="true"/>
      <dateFin xsi:nil="true"/>
      <preseance>20</preseance>
      <nominPrincipale>0</nominPrincipale>
      <infosQualite>
        <codeQualite>Membre</codeQualite>
        <libQualite>Membre</libQualite>
        <libQualiteSex>Membre</libQualiteSex>
      </infosQualite>
      <organes>
        <organeRef>PO733117</organeRef>
      </organes>
    </mandat>
    <mandat xmlns:xsi="http://www.w3.org/2001/XMLSchema-instance" xsi:type="MandatSimple_Type">
      <uid>PM739920</uid>
      <acteurRef>PA721262</acteurRef>
      <legislature>15</legislature>
      <typeOrgane>GA</typeOrgane>
      <dateDebut>2017-10-13</dateDebut>
      <datePublication xsi:nil="true"/>
      <dateFin xsi:nil="true"/>
      <preseance>20</preseance>
      <nominPrincipale>1</nominPrincipale>
      <infosQualite>
        <codeQualite>Membre</codeQualite>
        <libQualite>Membre</libQualite>
        <libQualiteSex>Membre</libQualiteSex>
      </infosQualite>
      <organes>
        <organeRef>PO733307</organeRef>
      </organes>
    </mandat>
    <mandat xmlns:xsi="http://www.w3.org/2001/XMLSchema-instance" xsi:type="MandatSimple_Type">
      <uid>PM739918</uid>
      <acteurRef>PA721262</acteurRef>
      <legislature>15</legislature>
      <typeOrgane>GA</typeOrgane>
      <dateDebut>2017-10-13</dateDebut>
      <datePublication xsi:nil="true"/>
      <dateFin xsi:nil="true"/>
      <preseance>20</preseance>
      <nominPrincipale>0</nominPrincipale>
      <infosQualite>
        <codeQualite>Membre</codeQualite>
        <libQualite>Membre</libQualite>
        <libQualiteSex>Membre</libQualiteSex>
      </infosQualite>
      <organes>
        <organeRef>PO733212</organeRef>
      </organes>
    </mandat>
    <mandat xmlns:xsi="http://www.w3.org/2001/XMLSchema-instance" xsi:type="MandatSimple_Type">
      <uid>PM739922</uid>
      <acteurRef>PA721262</acteurRef>
      <legislature>15</legislature>
      <typeOrgane>GA</typeOrgane>
      <dateDebut>2017-10-13</dateDebut>
      <datePublication xsi:nil="true"/>
      <dateFin xsi:nil="true"/>
      <preseance>20</preseance>
      <nominPrincipale>1</nominPrincipale>
      <infosQualite>
        <codeQualite>Membre</codeQualite>
        <libQualite>Membre</libQualite>
        <libQualiteSex>Membre</libQualiteSex>
      </infosQualite>
      <organes>
        <organeRef>PO733492</organeRef>
      </organes>
    </mandat>
    <mandat xmlns:xsi="http://www.w3.org/2001/XMLSchema-instance" xsi:type="MandatSimple_Type">
      <uid>PM742371</uid>
      <acteurRef>PA721262</acteurRef>
      <legislature>15</legislature>
      <typeOrgane>GA</typeOrgane>
      <dateDebut>2017-11-02</dateDebut>
      <datePublication xsi:nil="true"/>
      <dateFin xsi:nil="true"/>
      <preseance>20</preseance>
      <nominPrincipale>0</nominPrincipale>
      <infosQualite>
        <codeQualite>Membre</codeQualite>
        <libQualite>Membre</libQualite>
        <libQualiteSex>Membre</libQualiteSex>
      </infosQualite>
      <organes>
        <organeRef>PO733327</organeRef>
      </organes>
    </mandat>
    <mandat xmlns:xsi="http://www.w3.org/2001/XMLSchema-instance" xsi:type="MandatSimple_Type">
      <uid>PM739924</uid>
      <acteurRef>PA721262</acteurRef>
      <legislature>15</legislature>
      <typeOrgane>GA</typeOrgane>
      <dateDebut>2017-10-13</dateDebut>
      <datePublication xsi:nil="true"/>
      <dateFin xsi:nil="true"/>
      <preseance>20</preseance>
      <nominPrincipale>1</nominPrincipale>
      <infosQualite>
        <codeQualite>Membre</codeQualite>
        <libQualite>Membre</libQualite>
        <libQualiteSex>Membre</libQualiteSex>
      </infosQualite>
      <organes>
        <organeRef>PO733572</organeRef>
      </organes>
    </mandat>
    <mandat xmlns:xsi="http://www.w3.org/2001/XMLSchema-instance" xsi:type="MandatSimple_Type">
      <uid>PM739915</uid>
      <acteurRef>PA721262</acteurRef>
      <legislature>15</legislature>
      <typeOrgane>GA</typeOrgane>
      <dateDebut>2017-10-13</dateDebut>
      <datePublication xsi:nil="true"/>
      <dateFin xsi:nil="true"/>
      <preseance>20</preseance>
      <nominPrincipale>1</nominPrincipale>
      <infosQualite>
        <codeQualite>Membre</codeQualite>
        <libQualite>Membre</libQualite>
        <libQualiteSex>Membre</libQualiteSex>
      </infosQualite>
      <organes>
        <organeRef>PO732944</organeRef>
      </organes>
    </mandat>
    <mandat xmlns:xsi="http://www.w3.org/2001/XMLSchema-instance" xsi:type="MandatSimple_Type">
      <uid>PM739917</uid>
      <acteurRef>PA721262</acteurRef>
      <legislature>15</legislature>
      <typeOrgane>GA</typeOrgane>
      <dateDebut>2017-10-13</dateDebut>
      <datePublication xsi:nil="true"/>
      <dateFin xsi:nil="true"/>
      <preseance>20</preseance>
      <nominPrincipale>1</nominPrincipale>
      <infosQualite>
        <codeQualite>Membre</codeQualite>
        <libQualite>Membre</libQualite>
        <libQualiteSex>Membre</libQualiteSex>
      </infosQualite>
      <organes>
        <organeRef>PO733122</organeRef>
      </organes>
    </mandat>
    <mandat xmlns:xsi="http://www.w3.org/2001/XMLSchema-instance" xsi:type="MandatSimple_Type">
      <uid>PM739921</uid>
      <acteurRef>PA721262</acteurRef>
      <legislature>15</legislature>
      <typeOrgane>GA</typeOrgane>
      <dateDebut>2017-10-13</dateDebut>
      <datePublication xsi:nil="true"/>
      <dateFin xsi:nil="true"/>
      <preseance>20</preseance>
      <nominPrincipale>1</nominPrincipale>
      <infosQualite>
        <codeQualite>Membre</codeQualite>
        <libQualite>Membre</libQualite>
        <libQualiteSex>Membre</libQualiteSex>
      </infosQualite>
      <organes>
        <organeRef>PO733342</organeRef>
      </organes>
    </mandat>
    <mandat xmlns:xsi="http://www.w3.org/2001/XMLSchema-instance" xsi:type="MandatSimple_Type">
      <uid>PM739919</uid>
      <acteurRef>PA721262</acteurRef>
      <legislature>15</legislature>
      <typeOrgane>GA</typeOrgane>
      <dateDebut>2017-10-13</dateDebut>
      <datePublication xsi:nil="true"/>
      <dateFin xsi:nil="true"/>
      <preseance>20</preseance>
      <nominPrincipale>1</nominPrincipale>
      <infosQualite>
        <codeQualite>Membre</codeQualite>
        <libQualite>Membre</libQualite>
        <libQualiteSex>Membre</libQualiteSex>
      </infosQualite>
      <organes>
        <organeRef>PO733287</organeRef>
      </organes>
    </mandat>
    <mandat xmlns:xsi="http://www.w3.org/2001/XMLSchema-instance" xsi:type="MandatSimple_Type">
      <uid>PM739923</uid>
      <acteurRef>PA721262</acteurRef>
      <legislature>15</legislature>
      <typeOrgane>GA</typeOrgane>
      <dateDebut>2017-10-13</dateDebut>
      <datePublication xsi:nil="true"/>
      <dateFin xsi:nil="true"/>
      <preseance>20</preseance>
      <nominPrincipale>1</nominPrincipale>
      <infosQualite>
        <codeQualite>Membre</codeQualite>
        <libQualite>Membre</libQualite>
        <libQualiteSex>Membre</libQualiteSex>
      </infosQualite>
      <organes>
        <organeRef>PO733567</organeRef>
      </organes>
    </mandat>
    <mandat xmlns:xsi="http://www.w3.org/2001/XMLSchema-instance" xsi:type="MandatSimple_Type">
      <uid>PM739925</uid>
      <acteurRef>PA721262</acteurRef>
      <legislature>15</legislature>
      <typeOrgane>GA</typeOrgane>
      <dateDebut>2017-10-13</dateDebut>
      <datePublication xsi:nil="true"/>
      <dateFin xsi:nil="true"/>
      <preseance>20</preseance>
      <nominPrincipale>1</nominPrincipale>
      <infosQualite>
        <codeQualite>Membre</codeQualite>
        <libQualite>Membre</libQualite>
        <libQualiteSex>Membre</libQualiteSex>
      </infosQualite>
      <organes>
        <organeRef>PO733617</organeRef>
      </organes>
    </mandat>
    <mandat xmlns:xsi="http://www.w3.org/2001/XMLSchema-instance" xsi:type="MandatMission_Type">
      <uid>PM772925</uid>
      <acteurRef>PA721262</acteurRef>
      <legislature>15</legislature>
      <typeOrgane>MINISTERE</typeOrgane>
      <dateDebut>2020-06-24</dateDebut>
      <datePublication xsi:nil="true"/>
      <dateFin>2020-07-06</dateFin>
      <preseance>1</preseance>
      <nominPrincipale>1</nominPrincipale>
      <infosQualite>
        <codeQualite>en mission</codeQualite>
        <libQualite>en mission</libQualite>
        <libQualiteSex>en mission</libQualiteSex>
      </infosQualite>
      <organes>
        <organeRef>PO730017</organeRef>
      </organes>
      <libelle>La place des outre-mer dans l'environnement régional dans le contexte de la pandémie du covid-19</libelle>
      <missionSuivanteRef>PM773788</missionSuivanteRef>
      <missionPrecedenteRef xsi:nil="true"/>
    </mandat>
    <mandat xmlns:xsi="http://www.w3.org/2001/XMLSchema-instance" xsi:type="MandatMission_Type">
      <uid>PM760915</uid>
      <acteurRef>PA721262</acteurRef>
      <legislature>15</legislature>
      <typeOrgane>MINISTERE</typeOrgane>
      <dateDebut>2018-12-10</dateDebut>
      <datePublication>2018-12-11</datePublication>
      <dateFin>2019-06-09</dateFin>
      <preseance>1</preseance>
      <nominPrincipale>1</nominPrincipale>
      <infosQualite>
        <codeQualite>en mission</codeQualite>
        <libQualite>en mission</libQualite>
        <libQualiteSex>en mission</libQualiteSex>
      </infosQualite>
      <organes>
        <organeRef>PO759779</organeRef>
        <organeRef>PO759801</organeRef>
      </organes>
      <libelle>La formulation de propositions permettant de lutter efficacement contre l'habitat indigne</libelle>
      <missionSuivanteRef xsi:nil="true"/>
      <missionPrecedenteRef xsi:nil="true"/>
    </mandat>
    <mandat xmlns:xsi="http://www.w3.org/2001/XMLSchema-instance" xsi:type="MandatMission_Type">
      <uid>PM773788</uid>
      <acteurRef>PA721262</acteurRef>
      <legislature>15</legislature>
      <typeOrgane>MINISTERE</typeOrgane>
      <dateDebut>2020-07-07</dateDebut>
      <datePublication xsi:nil="true"/>
      <dateFin>2020-12-23</dateFin>
      <preseance>1</preseance>
      <nominPrincipale>1</nominPrincipale>
      <infosQualite>
        <codeQualite>en mission</codeQualite>
        <libQualite>en mission</libQualite>
        <libQualiteSex>en mission</libQualiteSex>
      </infosQualite>
      <organes>
        <organeRef>PO773388</organeRef>
      </organes>
      <libelle>La place des outre-mer dans l'environnement régional dans le contexte de la pandémie du covid-19</libelle>
      <missionSuivanteRef xsi:nil="true"/>
      <missionPrecedenteRef>PM772925</missionPrecedenteRef>
    </mandat>
    <mandat xmlns:xsi="http://www.w3.org/2001/XMLSchema-instance" xsi:type="MandatSimple_Type">
      <uid>PM785990</uid>
      <acteurRef>PA721262</acteurRef>
      <legislature>15</legislature>
      <typeOrgane>CMP</typeOrgane>
      <dateDebut>2021-09-30</dateDebut>
      <datePublication>2021-10-01</datePublication>
      <dateFin>2021-11-16</dateFin>
      <preseance>28</preseance>
      <nominPrincipale>1</nominPrincipale>
      <infosQualite>
        <codeQualite>Suppléant</codeQualite>
        <libQualite>Membre suppléant</libQualite>
        <libQualiteSex>Membre suppléant</libQualiteSex>
      </infosQualite>
      <organes>
        <organeRef>PO785819</organeRef>
      </organes>
    </mandat>
    <mandat xmlns:xsi="http://www.w3.org/2001/XMLSchema-instance" xsi:type="MandatSimple_Type">
      <uid>PM779024</uid>
      <acteurRef>PA721262</acteurRef>
      <legislature>15</legislature>
      <typeOrgane>CMP</typeOrgane>
      <dateDebut>2020-12-04</dateDebut>
      <datePublication>2020-12-10</datePublication>
      <dateFin>2020-12-11</dateFin>
      <preseance>28</preseance>
      <nominPrincipale>1</nominPrincipale>
      <infosQualite>
        <codeQualite>Suppléant</codeQualite>
        <libQualite>Membre suppléant</libQualite>
        <libQualiteSex>Membre suppléant</libQualiteSex>
      </infosQualite>
      <organes>
        <organeRef>PO778851</organeRef>
      </organes>
    </mandat>
    <mandat xmlns:xsi="http://www.w3.org/2001/XMLSchema-instance" xsi:type="MandatSimple_Type">
      <uid>PM759049</uid>
      <acteurRef>PA721262</acteurRef>
      <legislature>15</legislature>
      <typeOrgane>CMP</typeOrgane>
      <dateDebut>2018-09-25</dateDebut>
      <datePublication>2018-09-26</datePublication>
      <dateFin>2018-11-20</dateFin>
      <preseance>28</preseance>
      <nominPrincipale>1</nominPrincipale>
      <infosQualite>
        <codeQualite>Suppléant</codeQualite>
        <libQualite>Membre suppléant</libQualite>
        <libQualiteSex>Membre suppléant</libQualiteSex>
      </infosQualite>
      <organes>
        <organeRef>PO758375</organeRef>
      </organes>
    </mandat>
    <mandat xmlns:xsi="http://www.w3.org/2001/XMLSchema-instance" xsi:type="MandatSimple_Type">
      <uid>PM734211</uid>
      <acteurRef>PA721262</acteurRef>
      <legislature>15</legislature>
      <typeOrgane>CMP</typeOrgane>
      <dateDebut>2017-07-28</dateDebut>
      <datePublication>2017-07-28</datePublication>
      <dateFin>2017-08-01</dateFin>
      <preseance>28</preseance>
      <nominPrincipale>1</nominPrincipale>
      <infosQualite>
        <codeQualite>Suppléant</codeQualite>
        <libQualite>Membre suppléant</libQualite>
        <libQualiteSex>Membre suppléant</libQualiteSex>
      </infosQualite>
      <organes>
        <organeRef>PO733952</organeRef>
      </organes>
    </mandat>
    <mandat xmlns:xsi="http://www.w3.org/2001/XMLSchema-instance" xsi:type="MandatSimple_Type">
      <uid>PM756188</uid>
      <acteurRef>PA721262</acteurRef>
      <legislature>15</legislature>
      <typeOrgane>CMP</typeOrgane>
      <dateDebut>2018-05-17</dateDebut>
      <datePublication>2018-05-18</datePublication>
      <dateFin>2018-06-21</dateFin>
      <preseance>28</preseance>
      <nominPrincipale>1</nominPrincipale>
      <infosQualite>
        <codeQualite>Suppléant</codeQualite>
        <libQualite>Membre suppléant</libQualite>
        <libQualiteSex>Membre suppléant</libQualiteSex>
      </infosQualite>
      <organes>
        <organeRef>PO755798</organeRef>
      </organes>
    </mandat>
    <mandat xmlns:xsi="http://www.w3.org/2001/XMLSchema-instance" xsi:type="MandatSimple_Type">
      <uid>PM779003</uid>
      <acteurRef>PA721262</acteurRef>
      <legislature>15</legislature>
      <typeOrgane>CMP</typeOrgane>
      <dateDebut>2020-12-04</dateDebut>
      <datePublication>2020-12-10</datePublication>
      <dateFin>2020-12-11</dateFin>
      <preseance>28</preseance>
      <nominPrincipale>1</nominPrincipale>
      <infosQualite>
        <codeQualite>Suppléant</codeQualite>
        <libQualite>Membre suppléant</libQualite>
        <libQualiteSex>Membre suppléant</libQualiteSex>
      </infosQualite>
      <organes>
        <organeRef>PO778858</organeRef>
      </organes>
    </mandat>
    <mandat xmlns:xsi="http://www.w3.org/2001/XMLSchema-instance" xsi:type="MandatSimple_Type">
      <uid>PM758923</uid>
      <acteurRef>PA721262</acteurRef>
      <legislature>15</legislature>
      <typeOrgane>CMP</typeOrgane>
      <dateDebut>2018-09-13</dateDebut>
      <datePublication>2018-09-14</datePublication>
      <dateFin>2018-10-16</dateFin>
      <preseance>28</preseance>
      <nominPrincipale>1</nominPrincipale>
      <infosQualite>
        <codeQualite>Suppléant</codeQualite>
        <libQualite>Membre suppléant</libQualite>
        <libQualiteSex>Membre suppléant</libQualiteSex>
      </infosQualite>
      <organes>
        <organeRef>PO758352</organeRef>
      </organes>
    </mandat>
    <mandat xmlns:xsi="http://www.w3.org/2001/XMLSchema-instance" xsi:type="MandatSimple_Type">
      <uid>PM734168</uid>
      <acteurRef>PA721262</acteurRef>
      <legislature>15</legislature>
      <typeOrgane>CMP</typeOrgane>
      <dateDebut>2017-07-28</dateDebut>
      <datePublication>2017-07-28</datePublication>
      <dateFin>2017-08-01</dateFin>
      <preseance>28</preseance>
      <nominPrincipale>1</nominPrincipale>
      <infosQualite>
        <codeQualite>Suppléant</codeQualite>
        <libQualite>Membre suppléant</libQualite>
        <libQualiteSex>Membre suppléant</libQualiteSex>
      </infosQualite>
      <organes>
        <organeRef>PO733946</organeRef>
      </organes>
    </mandat>
    <mandat xmlns:xsi="http://www.w3.org/2001/XMLSchema-instance" xsi:type="MandatSimple_Type">
      <uid>PM773217</uid>
      <acteurRef>PA721262</acteurRef>
      <legislature>15</legislature>
      <typeOrgane>CMP</typeOrgane>
      <dateDebut>2020-07-02</dateDebut>
      <datePublication>2020-07-03</datePublication>
      <dateFin>2020-07-21</dateFin>
      <preseance>28</preseance>
      <nominPrincipale>1</nominPrincipale>
      <infosQualite>
        <codeQualite>Suppléant</codeQualite>
        <libQualite>Membre suppléant</libQualite>
        <libQualiteSex>Membre suppléant</libQualiteSex>
      </infosQualite>
      <organes>
        <organeRef>PO772400</organeRef>
      </organes>
    </mandat>
    <mandat xmlns:xsi="http://www.w3.org/2001/XMLSchema-instance" xsi:type="MandatSimple_Type">
      <uid>PM759076</uid>
      <acteurRef>PA721262</acteurRef>
      <legislature>15</legislature>
      <typeOrgane>CMP</typeOrgane>
      <dateDebut>2018-09-25</dateDebut>
      <datePublication>2018-09-26</datePublication>
      <dateFin>2018-11-20</dateFin>
      <preseance>28</preseance>
      <nominPrincipale>1</nominPrincipale>
      <infosQualite>
        <codeQualite>Suppléant</codeQualite>
        <libQualite>Membre suppléant</libQualite>
        <libQualiteSex>Membre suppléant</libQualiteSex>
      </infosQualite>
      <organes>
        <organeRef>PO758368</organeRef>
      </organes>
    </mandat>
    <mandat xmlns:xsi="http://www.w3.org/2001/XMLSchema-instance" xsi:type="MandatSimple_Type">
      <uid>PM765218</uid>
      <acteurRef>PA721262</acteurRef>
      <legislature>15</legislature>
      <typeOrgane>GE</typeOrgane>
      <dateDebut>2019-05-15</dateDebut>
      <datePublication xsi:nil="true"/>
      <dateFin xsi:nil="true"/>
      <preseance>8</preseance>
      <nominPrincipale>1</nominPrincipale>
      <infosQualite>
        <codeQualite>Vice-Président</codeQualite>
        <libQualite>Vice-Président</libQualite>
        <libQualiteSex>Vice-Président</libQualiteSex>
      </infosQualite>
      <organes>
        <organeRef>PO763229</organeRef>
      </organes>
    </mandat>
    <mandat xmlns:xsi="http://www.w3.org/2001/XMLSchema-instance" xsi:type="MandatSimple_Type">
      <uid>PM742530</uid>
      <acteurRef>PA721262</acteurRef>
      <legislature>15</legislature>
      <typeOrgane>GA</typeOrgane>
      <dateDebut>2017-10-24</dateDebut>
      <datePublication xsi:nil="true"/>
      <dateFin xsi:nil="true"/>
      <preseance>8</preseance>
      <nominPrincipale>1</nominPrincipale>
      <infosQualite>
        <codeQualite>Vice-Président</codeQualite>
        <libQualite>Vice-Président</libQualite>
        <libQualiteSex>Vice-Président</libQualiteSex>
      </infosQualite>
      <organes>
        <organeRef>PO732939</organeRef>
      </organes>
    </mandat>
    <mandat xmlns:xsi="http://www.w3.org/2001/XMLSchema-instance" xsi:type="MandatSimple_Type">
      <uid>PM784555</uid>
      <acteurRef>PA721262</acteurRef>
      <legislature>15</legislature>
      <typeOrgane>GA</typeOrgane>
      <dateDebut>2017-10-13</dateDebut>
      <datePublication xsi:nil="true"/>
      <dateFin xsi:nil="true"/>
      <preseance>8</preseance>
      <nominPrincipale>1</nominPrincipale>
      <infosQualite>
        <codeQualite>Vice-Président</codeQualite>
        <libQualite>Vice-Président</libQualite>
        <libQualiteSex>Vice-Président</libQualiteSex>
      </infosQualite>
      <organes>
        <organeRef>PO733212</organeRef>
      </organes>
    </mandat>
    <mandat xmlns:xsi="http://www.w3.org/2001/XMLSchema-instance" xsi:type="MandatSimple_Type">
      <uid>PM742372</uid>
      <acteurRef>PA721262</acteurRef>
      <legislature>15</legislature>
      <typeOrgane>GA</typeOrgane>
      <dateDebut>2017-11-02</dateDebut>
      <datePublication xsi:nil="true"/>
      <dateFin xsi:nil="true"/>
      <preseance>8</preseance>
      <nominPrincipale>1</nominPrincipale>
      <infosQualite>
        <codeQualite>Vice-Président</codeQualite>
        <libQualite>Vice-Président</libQualite>
        <libQualiteSex>Vice-Président</libQualiteSex>
      </infosQualite>
      <organes>
        <organeRef>PO733327</organeRef>
      </organes>
    </mandat>
    <mandat xmlns:xsi="http://www.w3.org/2001/XMLSchema-instance" xsi:type="MandatParlementaire_type">
      <uid>PM723218</uid>
      <acteurRef>PA721262</acteurRef>
      <legislature>15</legislature>
      <typeOrgane>ASSEMBLEE</typeOrgane>
      <dateDebut>2017-06-18</dateDebut>
      <datePublication xsi:nil="true"/>
      <dateFin xsi:nil="true"/>
      <preseance>50</preseance>
      <nominPrincipale>1</nominPrincipale>
      <infosQualite>
        <codeQualite>membre</codeQualite>
        <libQualite>membre</libQualite>
        <libQualiteSex>membre</libQualiteSex>
      </infosQualite>
      <organes>
        <organeRef>PO717460</organeRef>
      </organes>
      <suppleants>
        <suppleant>
          <dateDebut>2017-06-18</dateDebut>
          <dateFin xsi:nil="true"/>
          <suppleantRef>PA721266</suppleantRef>
        </suppleant>
      </suppleants>
      <chambre xsi:nil="true"/>
      <election>
        <lieu>
          <region>Ile-de-France</region>
          <regionType>Métropolitain</regionType>
          <departement>Val-d'Oise</departement>
          <numDepartement>95</numDepartement>
          <numCirco>2</numCirco>
        </lieu>
        <causeMandat>élections générales</causeMandat>
        <refCirconscription>PO718478</refCirconscription>
      </election>
      <mandature>
        <datePriseFonction>2017-06-21</datePriseFonction>
        <causeFin xsi:nil="true"/>
        <premiereElection>0</premiereElection>
        <placeHemicycle>373</placeHemicycle>
        <mandatRemplaceRef xsi:nil="true"/>
      </mandature>
      <collaborateurs>
        <collaborateur>
          <qualite>Mme</qualite>
          <prenom>Isabelle</prenom>
          <nom>Mercier</nom>
          <dateDebut xsi:nil="true"/>
          <dateFin xsi:nil="true"/>
        </collaborateur>
        <collaborateur>
          <qualite>Mme</qualite>
          <prenom>Claudie</prenom>
          <nom>Violette</nom>
          <dateDebut xsi:nil="true"/>
          <dateFin xsi:nil="true"/>
        </collaborateur>
        <collaborateur>
          <qualite>Mme</qualite>
          <prenom>Lou</prenom>
          <nom>Le Nabasque</nom>
          <dateDebut xsi:nil="true"/>
          <dateFin xsi:nil="true"/>
        </collaborateur>
        <collaborateur>
          <qualite>Mme</qualite>
          <prenom>Harielle</prenom>
          <nom>Lesueur</nom>
          <dateDebut xsi:nil="true"/>
          <dateFin xsi:nil="true"/>
        </collaborateur>
      </collaborateurs>
    </mandat>
  </mandats>
</acteur>
